[
  {
    "date": "2025-06-30",
    "symbol": "TECH",
    "reportedCurrency": "USD",
    "cik": "0000842023",
    "filingDate": "2025-08-22",
    "acceptedDate": "2025-08-22 06:31:16",
    "fiscalYear": "2025",
    "period": "FY",
    "revenue": 1219635000,
    "costOfRevenue": 429363000,
    "grossProfit": 790272000,
    "researchAndDevelopmentExpenses": 99496000,
    "generalAndAdministrativeExpenses": 415097000,
    "sellingAndMarketingExpenses": 0,
    "sellingGeneralAndAdministrativeExpenses": 415097000,
    "otherExpenses": 173424000,
    "operatingExpenses": 688017000,
    "costAndExpenses": 1117380000,
    "netInterestIncome": -4623000,
    "interestIncome": 3886000,
    "interestExpense": 8509000,
    "depreciationAndAmortization": 109903000,
    "ebitda": 216875000,
    "ebit": 106972000,
    "nonOperatingIncomeExcludingInterest": -4717000,
    "operatingIncome": 102255000,
    "totalOtherIncomeExpensesNet": -3792000,
    "incomeBeforeTax": 98463000,
    "incomeTaxExpense": 25063000,
    "netIncomeFromContinuingOperations": 73400000,
    "netIncomeFromDiscontinuedOperations": 0,
    "otherAdjustmentsToNetIncome": 0,
    "netIncome": 73400000,
    "netIncomeDeductions": 0,
    "bottomLineNetIncome": 73363000,
    "eps": 0.47,
    "epsDiluted": 0.46,
    "weightedAverageShsOut": 157521000,
    "weightedAverageShsOutDil": 159717000
  },
  {
    "date": "2024-06-30",
    "symbol": "TECH",
    "reportedCurrency": "USD",
    "cik": "0000842023",
    "filingDate": "2024-08-22",
    "acceptedDate": "2024-08-22 16:30:35",
    "fiscalYear": "2024",
    "period": "FY",
    "revenue": 1159060000,
    "costOfRevenue": 389335000,
    "grossProfit": 769725000,
    "researchAndDevelopmentExpenses": 96664000,
    "generalAndAdministrativeExpenses": 393320000,
    "sellingAndMarketingExpenses": 0,
    "sellingGeneralAndAdministrativeExpenses": 393320000,
    "otherExpenses": 73055000,
    "operatingExpenses": 563039000,
    "costAndExpenses": 952374000,
    "netInterestIncome": -12413000,
    "interestIncome": 3323000,
    "interestExpense": 15736000,
    "depreciationAndAmortization": 111711000,
    "ebitda": 313136000,
    "ebit": 201425000,
    "nonOperatingIncomeExcludingInterest": 5261000,
    "operatingIncome": 206686000,
    "totalOtherIncomeExpensesNet": -20997000,
    "incomeBeforeTax": 185689000,
    "incomeTaxExpense": 17584000,
    "netIncomeFromContinuingOperations": 168105000,
    "netIncomeFromDiscontinuedOperations": 0,
    "otherAdjustmentsToNetIncome": 0,
    "netIncome": 168105000,
    "netIncomeDeductions": 0,
    "bottomLineNetIncome": 168072000,
    "eps": 1.07,
    "epsDiluted": 1.05,
    "weightedAverageShsOut": 157708000,
    "weightedAverageShsOutDil": 160774000
  },
  {
    "date": "2023-06-30",
    "symbol": "TECH",
    "reportedCurrency": "USD",
    "cik": "0000842023",
    "filingDate": "2023-08-23",
    "acceptedDate": "2023-08-23 16:30:51",
    "fiscalYear": "2023",
    "period": "FY",
    "revenue": 1136702000,
    "costOfRevenue": 366887000,
    "grossProfit": 769815000,
    "researchAndDevelopmentExpenses": 92493000,
    "generalAndAdministrativeExpenses": 352438000,
    "sellingAndMarketingExpenses": 0,
    "sellingGeneralAndAdministrativeExpenses": 352438000,
    "otherExpenses": 25940000,
    "operatingExpenses": 470871000,
    "costAndExpenses": 837758000,
    "netInterestIncome": -7805000,
    "interestIncome": 3410000,
    "interestExpense": 11215000,
    "depreciationAndAmortization": 107238000,
    "ebitda": 457112000,
    "ebit": 349874000,
    "nonOperatingIncomeExcludingInterest": -50930000,
    "operatingIncome": 298944000,
    "totalOtherIncomeExpensesNet": 39715000,
    "incomeBeforeTax": 338659000,
    "incomeTaxExpense": 53217000,
    "netIncomeFromContinuingOperations": 285442000,
    "netIncomeFromDiscontinuedOperations": 0,
    "otherAdjustmentsToNetIncome": 0,
    "netIncome": 285263000,
    "netIncomeDeductions": 0,
    "bottomLineNetIncome": 285193000,
    "eps": 1.81,
    "epsDiluted": 1.76,
    "weightedAverageShsOut": 157179000,
    "weightedAverageShsOutDil": 161855000
  },
  {
    "date": "2022-06-30",
    "symbol": "TECH",
    "reportedCurrency": "USD",
    "cik": "0000842023",
    "filingDate": "2022-08-24",
    "acceptedDate": "2022-08-24 16:31:27",
    "fiscalYear": "2022",
    "period": "FY",
    "revenue": 1105599000,
    "costOfRevenue": 349103000,
    "grossProfit": 756496000,
    "researchAndDevelopmentExpenses": 87140000,
    "generalAndAdministrativeExpenses": 339001000,
    "sellingAndMarketingExpenses": 0,
    "sellingGeneralAndAdministrativeExpenses": 339001000,
    "otherExpenses": 33765000,
    "operatingExpenses": 459906000,
    "costAndExpenses": 809009000,
    "netInterestIncome": -10515000,
    "interestIncome": 794000,
    "interestExpense": 11309000,
    "depreciationAndAmortization": 101069000,
    "ebitda": 413764000,
    "ebit": 312695000,
    "nonOperatingIncomeExcludingInterest": -16105000,
    "operatingIncome": 296590000,
    "totalOtherIncomeExpensesNet": 4796000,
    "incomeBeforeTax": 301386000,
    "incomeTaxExpense": 38287000,
    "netIncomeFromContinuingOperations": 263099000,
    "netIncomeFromDiscontinuedOperations": 0,
    "otherAdjustmentsToNetIncome": 0,
    "netIncome": 272051000,
    "netIncomeDeductions": 0,
    "bottomLineNetIncome": 271930000,
    "eps": 1.73,
    "epsDiluted": 1.66,
    "weightedAverageShsOut": 156876000,
    "weightedAverageShsOutDil": 164116000
  },
  {
    "date": "2021-06-30",
    "symbol": "TECH",
    "reportedCurrency": "USD",
    "cik": "0000842023",
    "filingDate": "2021-08-25",
    "acceptedDate": "2021-08-25 16:46:35",
    "fiscalYear": "2021",
    "period": "FY",
    "revenue": 931032000,
    "costOfRevenue": 298182000,
    "grossProfit": 632850000,
    "researchAndDevelopmentExpenses": 70603000,
    "generalAndAdministrativeExpenses": 289924000,
    "sellingAndMarketingExpenses": 0,
    "sellingGeneralAndAdministrativeExpenses": 289924000,
    "otherExpenses": 35027000,
    "operatingExpenses": 395554000,
    "costAndExpenses": 693736000,
    "netInterestIncome": -13479000,
    "interestIncome": 473000,
    "interestExpense": 13952000,
    "depreciationAndAmortization": 87747000,
    "ebitda": 249874000,
    "ebit": 162127000,
    "nonOperatingIncomeExcludingInterest": 75169000,
    "operatingIncome": 237296000,
    "totalOtherIncomeExpensesNet": -89121000,
    "incomeBeforeTax": 148175000,
    "incomeTaxExpense": 8590000,
    "netIncomeFromContinuingOperations": 139585000,
    "netIncomeFromDiscontinuedOperations": 0,
    "otherAdjustmentsToNetIncome": 0,
    "netIncome": 140410000,
    "netIncomeDeductions": 0,
    "bottomLineNetIncome": 140324000,
    "eps": 0.91,
    "epsDiluted": 0.87,
    "weightedAverageShsOut": 154988000,
    "weightedAverageShsOutDil": 161932000
  },
  {
    "date": "2020-06-30",
    "symbol": "TECH",
    "reportedCurrency": "USD",
    "cik": "0000842023",
    "filingDate": "2020-08-26",
    "acceptedDate": "2020-08-26 16:36:54",
    "fiscalYear": "2020",
    "period": "FY",
    "revenue": 738691000,
    "costOfRevenue": 255497000,
    "grossProfit": 483194000,
    "researchAndDevelopmentExpenses": 65192000,
    "generalAndAdministrativeExpenses": 240882000,
    "sellingAndMarketingExpenses": 0,
    "sellingGeneralAndAdministrativeExpenses": 240882000,
    "otherExpenses": 19701000,
    "operatingExpenses": 325775000,
    "costAndExpenses": 581272000,
    "netInterestIncome": -18592000,
    "interestIncome": 605000,
    "interestExpense": 19197000,
    "depreciationAndAmortization": 82737000,
    "ebitda": 378411000,
    "ebit": 295674000,
    "nonOperatingIncomeExcludingInterest": -138255000,
    "operatingIncome": 157419000,
    "totalOtherIncomeExpensesNet": 119058000,
    "incomeBeforeTax": 276477000,
    "incomeTaxExpense": 47181000,
    "netIncomeFromContinuingOperations": 229296000,
    "netIncomeFromDiscontinuedOperations": 0,
    "otherAdjustmentsToNetIncome": 0,
    "netIncome": 229296000,
    "netIncomeDeductions": 0,
    "bottomLineNetIncome": 229072000,
    "eps": 1.5,
    "epsDiluted": 1.45,
    "weightedAverageShsOut": 152804000,
    "weightedAverageShsOutDil": 157604000
  },
  {
    "date": "2019-06-30",
    "symbol": "TECH",
    "reportedCurrency": "USD",
    "cik": "0000842023",
    "filingDate": "2019-08-28",
    "acceptedDate": "2019-08-28 16:16:47",
    "fiscalYear": "2019",
    "period": "FY",
    "revenue": 714006000,
    "costOfRevenue": 240515000,
    "grossProfit": 473491000,
    "researchAndDevelopmentExpenses": 62413000,
    "generalAndAdministrativeExpenses": 236867000,
    "sellingAndMarketingExpenses": 27492000,
    "sellingGeneralAndAdministrativeExpenses": 264359000,
    "otherExpenses": 0,
    "operatingExpenses": 326772000,
    "costAndExpenses": 567287000,
    "netInterestIncome": -21136000,
    "interestIncome": 569000,
    "interestExpense": 21705000,
    "depreciationAndAmortization": 78171000,
    "ebitda": 211891000,
    "ebit": 133720000,
    "nonOperatingIncomeExcludingInterest": 12999000,
    "operatingIncome": 125583000,
    "totalOtherIncomeExpensesNet": -34704000,
    "incomeBeforeTax": 112015000,
    "incomeTaxExpense": 15943000,
    "netIncomeFromContinuingOperations": 96072000,
    "netIncomeFromDiscontinuedOperations": 0,
    "otherAdjustmentsToNetIncome": 0,
    "netIncome": 96072000,
    "netIncomeDeductions": 0,
    "bottomLineNetIncome": 95967000,
    "eps": 0.64,
    "epsDiluted": 0.62,
    "weightedAverageShsOut": 151124000,
    "weightedAverageShsOutDil": 155568000
  },
  {
    "date": "2018-06-30",
    "symbol": "TECH",
    "reportedCurrency": "USD",
    "cik": "0000842023",
    "filingDate": "2018-08-27",
    "acceptedDate": "2018-08-27 16:47:54",
    "fiscalYear": "2018",
    "period": "FY",
    "revenue": 642993000,
    "costOfRevenue": 210850000,
    "grossProfit": 432143000,
    "researchAndDevelopmentExpenses": 55329000,
    "generalAndAdministrativeExpenses": 240636000,
    "sellingAndMarketingExpenses": 0,
    "sellingGeneralAndAdministrativeExpenses": 240636000,
    "otherExpenses": 0,
    "operatingExpenses": 295965000,
    "costAndExpenses": 506815000,
    "netInterestIncome": -9779000,
    "interestIncome": 409000,
    "interestExpense": 10188000,
    "depreciationAndAmortization": 64463000,
    "ebitda": 200603000,
    "ebit": 136140000,
    "nonOperatingIncomeExcludingInterest": 38000,
    "operatingIncome": 136178000,
    "totalOtherIncomeExpensesNet": -10226000,
    "incomeBeforeTax": 125952000,
    "incomeTaxExpense": -602000,
    "netIncomeFromContinuingOperations": 126150000,
    "netIncomeFromDiscontinuedOperations": 0,
    "otherAdjustmentsToNetIncome": 0,
    "netIncome": 125350000,
    "netIncomeDeductions": 0,
    "bottomLineNetIncome": 126042000,
    "eps": 0.84,
    "epsDiluted": 0.82,
    "weightedAverageShsOut": 149904000,
    "weightedAverageShsOutDil": 152220000
  },
  {
    "date": "2017-06-30",
    "symbol": "TECH",
    "reportedCurrency": "USD",
    "cik": "0000842023",
    "filingDate": "2017-09-07",
    "acceptedDate": "2017-09-07 17:06:02",
    "fiscalYear": "2017",
    "period": "FY",
    "revenue": 563003000,
    "costOfRevenue": 188462000,
    "grossProfit": 374541000,
    "researchAndDevelopmentExpenses": 53514000,
    "generalAndAdministrativeExpenses": 153326000,
    "sellingAndMarketingExpenses": 45917000,
    "sellingGeneralAndAdministrativeExpenses": 199243000,
    "otherExpenses": 0,
    "operatingExpenses": 252757000,
    "costAndExpenses": 441219000,
    "netInterestIncome": -7057000,
    "interestIncome": 304000,
    "interestExpense": 7361000,
    "depreciationAndAmortization": 60036000,
    "ebitda": 179358000,
    "ebit": 119322000,
    "nonOperatingIncomeExcludingInterest": 1262000,
    "operatingIncome": 121784000,
    "totalOtherIncomeExpensesNet": -8623000,
    "incomeBeforeTax": 113161000,
    "incomeTaxExpense": 35875000,
    "netIncomeFromContinuingOperations": 76086000,
    "netIncomeFromDiscontinuedOperations": 0,
    "otherAdjustmentsToNetIncome": 0,
    "netIncome": 77286000,
    "netIncomeDeductions": 0,
    "bottomLineNetIncome": 76021000,
    "eps": 0.52,
    "epsDiluted": 0.52,
    "weightedAverageShsOut": 149252000,
    "weightedAverageShsOutDil": 150000000
  },
  {
    "date": "2016-06-30",
    "symbol": "TECH",
    "reportedCurrency": "USD",
    "cik": "0000842023",
    "filingDate": "2016-08-29",
    "acceptedDate": "2016-08-29 16:49:57",
    "fiscalYear": "2016",
    "period": "FY",
    "revenue": 499023000,
    "costOfRevenue": 162364000,
    "grossProfit": 336659000,
    "researchAndDevelopmentExpenses": 45187000,
    "generalAndAdministrativeExpenses": 140879000,
    "sellingAndMarketingExpenses": 0,
    "sellingGeneralAndAdministrativeExpenses": 140879000,
    "otherExpenses": 0,
    "operatingExpenses": 186066000,
    "costAndExpenses": 348430000,
    "netInterestIncome": -1499000,
    "interestIncome": 249000,
    "interestExpense": 1748000,
    "depreciationAndAmortization": 42764000,
    "ebitda": 191993000,
    "ebit": 149229000,
    "nonOperatingIncomeExcludingInterest": 1364000,
    "operatingIncome": 150593000,
    "totalOtherIncomeExpensesNet": -3112000,
    "incomeBeforeTax": 147481000,
    "incomeTaxExpense": 43005000,
    "netIncomeFromContinuingOperations": 104476000,
    "netIncomeFromDiscontinuedOperations": 0,
    "otherAdjustmentsToNetIncome": 0,
    "netIncome": 104476000,
    "netIncomeDeductions": 7.501512300223112e-9,
    "bottomLineNetIncome": 104424000,
    "eps": 0.7,
    "epsDiluted": 0.7,
    "weightedAverageShsOut": 148776000,
    "weightedAverageShsOutDil": 149304000
  },
  {
    "date": "2015-06-30",
    "symbol": "TECH",
    "reportedCurrency": "USD",
    "cik": "0000842023",
    "filingDate": "2015-08-31",
    "acceptedDate": "2015-08-31 16:48:02",
    "fiscalYear": "2015",
    "period": "FY",
    "revenue": 452246000,
    "costOfRevenue": 144969000,
    "grossProfit": 307277000,
    "researchAndDevelopmentExpenses": 40853000,
    "generalAndAdministrativeExpenses": 119401000,
    "sellingAndMarketingExpenses": 0,
    "sellingGeneralAndAdministrativeExpenses": 119401000,
    "otherExpenses": 0,
    "operatingExpenses": 160254000,
    "costAndExpenses": 305223000,
    "netInterestIncome": -910000,
    "interestIncome": 634000,
    "interestExpense": 1544000,
    "depreciationAndAmortization": 37226000,
    "ebitda": 192932000,
    "ebit": 155706000,
    "nonOperatingIncomeExcludingInterest": -8683000,
    "operatingIncome": 147023000,
    "totalOtherIncomeExpensesNet": 7139000,
    "incomeBeforeTax": 154162000,
    "incomeTaxExpense": 46427000,
    "netIncomeFromContinuingOperations": 107735000,
    "netIncomeFromDiscontinuedOperations": 0,
    "otherAdjustmentsToNetIncome": 0,
    "netIncome": 107735000,
    "netIncomeDeductions": 0,
    "bottomLineNetIncome": 107735000,
    "eps": 0.73,
    "epsDiluted": 0.72,
    "weightedAverageShsOut": 148384000,
    "weightedAverageShsOutDil": 148924000
  },
  {
    "date": "2014-06-30",
    "symbol": "TECH",
    "reportedCurrency": "USD",
    "cik": "0000842023",
    "filingDate": "2014-08-29",
    "acceptedDate": "2014-08-29 17:04:39",
    "fiscalYear": "2014",
    "period": "FY",
    "revenue": 357763000,
    "costOfRevenue": 106352000,
    "grossProfit": 251411000,
    "researchAndDevelopmentExpenses": 30945000,
    "generalAndAdministrativeExpenses": 60716000,
    "sellingAndMarketingExpenses": 0,
    "sellingGeneralAndAdministrativeExpenses": 60716000,
    "otherExpenses": 0,
    "operatingExpenses": 91661000,
    "costAndExpenses": 198013000,
    "netInterestIncome": 2684000,
    "interestIncome": 2684000,
    "interestExpense": 0,
    "depreciationAndAmortization": 19175000,
    "ebitda": 180567000,
    "ebit": 161392000,
    "nonOperatingIncomeExcludingInterest": -1642000,
    "operatingIncome": 159750000,
    "totalOtherIncomeExpensesNet": 1642000,
    "incomeBeforeTax": 161392000,
    "incomeTaxExpense": 50444000,
    "netIncomeFromContinuingOperations": 110948000,
    "netIncomeFromDiscontinuedOperations": 0,
    "otherAdjustmentsToNetIncome": 0,
    "netIncome": 110948000,
    "netIncomeDeductions": 0,
    "bottomLineNetIncome": 110948000,
    "eps": 0.75,
    "epsDiluted": 0.75,
    "weightedAverageShsOut": 147560000,
    "weightedAverageShsOutDil": 148020000
  },
  {
    "date": "2013-06-30",
    "symbol": "TECH",
    "reportedCurrency": "USD",
    "cik": "0000842023",
    "filingDate": "2013-08-29",
    "acceptedDate": "2013-08-29 15:37:26",
    "fiscalYear": "2013",
    "period": "FY",
    "revenue": 310575000,
    "costOfRevenue": 79465000,
    "grossProfit": 231110000,
    "researchAndDevelopmentExpenses": 29257000,
    "generalAndAdministrativeExpenses": 43384000,
    "sellingAndMarketingExpenses": 0,
    "sellingGeneralAndAdministrativeExpenses": 43384000,
    "otherExpenses": 830000,
    "operatingExpenses": 74833000,
    "costAndExpenses": 154298000,
    "netInterestIncome": 2646000,
    "interestIncome": 2646000,
    "interestExpense": 0,
    "depreciationAndAmortization": 12321000,
    "ebitda": 172983000,
    "ebit": 160662000,
    "nonOperatingIncomeExcludingInterest": -2193000,
    "operatingIncome": 158469000,
    "totalOtherIncomeExpensesNet": 2193000,
    "incomeBeforeTax": 160662000,
    "incomeTaxExpense": 48101000,
    "netIncomeFromContinuingOperations": 112561000,
    "netIncomeFromDiscontinuedOperations": 0,
    "otherAdjustmentsToNetIncome": 0,
    "netIncome": 112561000,
    "netIncomeDeductions": 0,
    "bottomLineNetIncome": 112561000,
    "eps": 0.76,
    "epsDiluted": 0.76,
    "weightedAverageShsOut": 147344000,
    "weightedAverageShsOutDil": 147600000
  },
  {
    "date": "2012-06-30",
    "symbol": "TECH",
    "reportedCurrency": "USD",
    "cik": "0000842023",
    "filingDate": "2012-08-29",
    "acceptedDate": "2012-08-29 08:48:59",
    "fiscalYear": "2012",
    "period": "FY",
    "revenue": 314560000,
    "costOfRevenue": 78756000,
    "grossProfit": 235804000,
    "researchAndDevelopmentExpenses": 27912000,
    "generalAndAdministrativeExpenses": 41683000,
    "sellingAndMarketingExpenses": 0,
    "sellingGeneralAndAdministrativeExpenses": 41683000,
    "otherExpenses": 693000,
    "operatingExpenses": 71722000,
    "costAndExpenses": 150478000,
    "netInterestIncome": 2639000,
    "interestIncome": 2639000,
    "interestExpense": 0,
    "depreciationAndAmortization": 12467000,
    "ebitda": 174662000,
    "ebit": 164082000,
    "nonOperatingIncomeExcludingInterest": 2127000,
    "operatingIncome": 166209000,
    "totalOtherIncomeExpensesNet": -4014000,
    "incomeBeforeTax": 162195000,
    "incomeTaxExpense": 49864000,
    "netIncomeFromContinuingOperations": 112331000,
    "netIncomeFromDiscontinuedOperations": 0,
    "otherAdjustmentsToNetIncome": 0,
    "netIncome": 112331000,
    "netIncomeDeductions": 0,
    "bottomLineNetIncome": 112331000,
    "eps": 0.76,
    "epsDiluted": 0.76,
    "weightedAverageShsOut": 147756000,
    "weightedAverageShsOutDil": 148024000
  },
  {
    "date": "2011-06-30",
    "symbol": "TECH",
    "reportedCurrency": "USD",
    "cik": "0000842023",
    "filingDate": "2011-08-29",
    "acceptedDate": "2011-08-29 12:12:46",
    "fiscalYear": "2011",
    "period": "FY",
    "revenue": 289962000,
    "costOfRevenue": 65025000,
    "grossProfit": 224937000,
    "researchAndDevelopmentExpenses": 25985000,
    "generalAndAdministrativeExpenses": 35897000,
    "sellingAndMarketingExpenses": 0,
    "sellingGeneralAndAdministrativeExpenses": 35897000,
    "otherExpenses": 0,
    "operatingExpenses": 61882000,
    "costAndExpenses": 126907000,
    "netInterestIncome": 3752000,
    "interestIncome": 3752000,
    "interestExpense": 0,
    "depreciationAndAmortization": 8700000,
    "ebitda": 173681000,
    "ebit": 160762000,
    "nonOperatingIncomeExcludingInterest": 2293000,
    "operatingIncome": 163055000,
    "totalOtherIncomeExpensesNet": 1926000,
    "incomeBeforeTax": 164981000,
    "incomeTaxExpense": 52679000,
    "netIncomeFromContinuingOperations": 112302000,
    "netIncomeFromDiscontinuedOperations": 0,
    "otherAdjustmentsToNetIncome": 0,
    "netIncome": 112302000,
    "netIncomeDeductions": 0,
    "bottomLineNetIncome": 112302000,
    "eps": 0.76,
    "epsDiluted": 0.76,
    "weightedAverageShsOut": 148392000,
    "weightedAverageShsOutDil": 148688000
  },
  {
    "date": "2010-06-30",
    "symbol": "TECH",
    "reportedCurrency": "USD",
    "cik": "0000842023",
    "filingDate": "2010-08-27",
    "acceptedDate": "2010-08-27 10:36:50",
    "fiscalYear": "2010",
    "period": "FY",
    "revenue": 269047000,
    "costOfRevenue": 54463000,
    "grossProfit": 214584000,
    "researchAndDevelopmentExpenses": 25121000,
    "generalAndAdministrativeExpenses": 32175000,
    "sellingAndMarketingExpenses": 0,
    "sellingGeneralAndAdministrativeExpenses": 32175000,
    "otherExpenses": 960000,
    "operatingExpenses": 58256000,
    "costAndExpenses": 112719000,
    "netInterestIncome": 4375000,
    "interestIncome": 4375000,
    "interestExpense": 0,
    "depreciationAndAmortization": 960000,
    "ebitda": 164576000,
    "ebit": 154128000,
    "nonOperatingIncomeExcludingInterest": 2200000,
    "operatingIncome": 156328000,
    "totalOtherIncomeExpensesNet": 118000,
    "incomeBeforeTax": 156446000,
    "incomeTaxExpense": 46670000,
    "netIncomeFromContinuingOperations": 109776000,
    "netIncomeFromDiscontinuedOperations": 0,
    "otherAdjustmentsToNetIncome": 0,
    "netIncome": 109776000,
    "netIncomeDeductions": 0,
    "bottomLineNetIncome": 109776000,
    "eps": 0.74,
    "epsDiluted": 0.73,
    "weightedAverageShsOut": 149020000,
    "weightedAverageShsOutDil": 149388000
  },
  {
    "date": "2009-06-30",
    "symbol": "TECH",
    "reportedCurrency": "USD",
    "cik": "0000842023",
    "filingDate": "2009-08-28",
    "acceptedDate": "2009-08-28 10:18:03",
    "fiscalYear": "2009",
    "period": "FY",
    "revenue": 263956000,
    "costOfRevenue": 55488000,
    "grossProfit": 208468000,
    "researchAndDevelopmentExpenses": 23564000,
    "generalAndAdministrativeExpenses": 33164000,
    "sellingAndMarketingExpenses": 0,
    "sellingGeneralAndAdministrativeExpenses": 33164000,
    "otherExpenses": 960000,
    "operatingExpenses": 57688000,
    "costAndExpenses": 113176000,
    "netInterestIncome": 7634000,
    "interestIncome": 7634000,
    "interestExpense": 0,
    "depreciationAndAmortization": 7766000,
    "ebitda": 158546000,
    "ebit": 150780000,
    "nonOperatingIncomeExcludingInterest": 0,
    "operatingIncome": 150780000,
    "totalOtherIncomeExpensesNet": 4583000,
    "incomeBeforeTax": 155363000,
    "incomeTaxExpense": 50121000,
    "netIncomeFromContinuingOperations": 105242000,
    "netIncomeFromDiscontinuedOperations": 0,
    "otherAdjustmentsToNetIncome": 0,
    "netIncome": 105242000,
    "netIncomeDeductions": 0,
    "bottomLineNetIncome": 105242000,
    "eps": 0.7,
    "epsDiluted": 0.69,
    "weightedAverageShsOut": 151208000,
    "weightedAverageShsOutDil": 151600000
  },
  {
    "date": "2008-06-30",
    "symbol": "TECH",
    "reportedCurrency": "USD",
    "cik": "0000842023",
    "filingDate": "2008-08-28",
    "acceptedDate": "2008-08-28 13:01:56",
    "fiscalYear": "2008",
    "period": "FY",
    "revenue": 257420000,
    "costOfRevenue": 52889000,
    "grossProfit": 204531000,
    "researchAndDevelopmentExpenses": 22394000,
    "generalAndAdministrativeExpenses": 36715000,
    "sellingAndMarketingExpenses": 0,
    "sellingGeneralAndAdministrativeExpenses": 36715000,
    "otherExpenses": 1135000,
    "operatingExpenses": 60244000,
    "costAndExpenses": 113133000,
    "netInterestIncome": 12188000,
    "interestIncome": 12188000,
    "interestExpense": 0,
    "depreciationAndAmortization": 7259000,
    "ebitda": 151546000,
    "ebit": 144287000,
    "nonOperatingIncomeExcludingInterest": 0,
    "operatingIncome": 144287000,
    "totalOtherIncomeExpensesNet": 9544000,
    "incomeBeforeTax": 153831000,
    "incomeTaxExpense": 50273000,
    "netIncomeFromContinuingOperations": 103558000,
    "netIncomeFromDiscontinuedOperations": 0,
    "otherAdjustmentsToNetIncome": 0,
    "netIncome": 103558000,
    "netIncomeDeductions": 0,
    "bottomLineNetIncome": 103558000,
    "eps": 0.66,
    "epsDiluted": 0.66,
    "weightedAverageShsOut": 156556000,
    "weightedAverageShsOutDil": 156988000
  },
  {
    "date": "2007-06-30",
    "symbol": "TECH",
    "reportedCurrency": "USD",
    "cik": "0000842023",
    "filingDate": "2007-08-29",
    "acceptedDate": "2007-08-29 09:48:00",
    "fiscalYear": "2007",
    "period": "FY",
    "revenue": 223482000,
    "costOfRevenue": 46667000,
    "grossProfit": 176815000,
    "researchAndDevelopmentExpenses": 20082000,
    "generalAndAdministrativeExpenses": 30965000,
    "sellingAndMarketingExpenses": 0,
    "sellingGeneralAndAdministrativeExpenses": 30965000,
    "otherExpenses": 1614000,
    "operatingExpenses": 52661000,
    "costAndExpenses": 99328000,
    "netInterestIncome": 7351000,
    "interestIncome": 8434000,
    "interestExpense": 1083000,
    "depreciationAndAmortization": 6994000,
    "ebitda": 137008000,
    "ebit": 130014000,
    "nonOperatingIncomeExcludingInterest": -5860000,
    "operatingIncome": 124154000,
    "totalOtherIncomeExpensesNet": 4777000,
    "incomeBeforeTax": 128931000,
    "incomeTaxExpense": 43820000,
    "netIncomeFromContinuingOperations": 85111000,
    "netIncomeFromDiscontinuedOperations": 0,
    "otherAdjustmentsToNetIncome": 0,
    "netIncome": 85111000,
    "netIncomeDeductions": 0,
    "bottomLineNetIncome": 85111000,
    "eps": 0.54,
    "epsDiluted": 0.54,
    "weightedAverageShsOut": 157624000,
    "weightedAverageShsOutDil": 158052000
  },
  {
    "date": "2006-06-30",
    "symbol": "TECH",
    "reportedCurrency": "USD",
    "cik": "0000842023",
    "filingDate": "2006-08-30",
    "acceptedDate": "2006-08-30 10:40:58",
    "fiscalYear": "2006",
    "period": "FY",
    "revenue": 202617000,
    "costOfRevenue": 45718000,
    "grossProfit": 156899000,
    "researchAndDevelopmentExpenses": 18825000,
    "generalAndAdministrativeExpenses": 27604000,
    "sellingAndMarketingExpenses": 0,
    "sellingGeneralAndAdministrativeExpenses": 27604000,
    "otherExpenses": 1967000,
    "operatingExpenses": 48396000,
    "costAndExpenses": 94114000,
    "netInterestIncome": 0,
    "interestIncome": 0,
    "interestExpense": 0,
    "depreciationAndAmortization": 6955000,
    "ebitda": 115458000,
    "ebit": 108503000,
    "nonOperatingIncomeExcludingInterest": 0,
    "operatingIncome": 108503000,
    "totalOtherIncomeExpensesNet": 2660000,
    "incomeBeforeTax": 111163000,
    "incomeTaxExpense": 37812000,
    "netIncomeFromContinuingOperations": 73351000,
    "netIncomeFromDiscontinuedOperations": 0,
    "otherAdjustmentsToNetIncome": 0,
    "netIncome": 73351000,
    "netIncomeDeductions": 0,
    "bottomLineNetIncome": 73351000,
    "eps": 0.47,
    "epsDiluted": 0.46,
    "weightedAverageShsOut": 156196000,
    "weightedAverageShsOutDil": 158376000
  },
  {
    "date": "2005-06-30",
    "symbol": "TECH",
    "reportedCurrency": "USD",
    "cik": "0000842023",
    "filingDate": "2005-09-12",
    "acceptedDate": "2005-09-12 16:16:31",
    "fiscalYear": "2005",
    "period": "FY",
    "revenue": 178652000,
    "costOfRevenue": 36813000,
    "grossProfit": 141839000,
    "researchAndDevelopmentExpenses": 18379000,
    "generalAndAdministrativeExpenses": 24476000,
    "sellingAndMarketingExpenses": 0,
    "sellingGeneralAndAdministrativeExpenses": 24476000,
    "otherExpenses": 1221000,
    "operatingExpenses": 44076000,
    "costAndExpenses": 80889000,
    "netInterestIncome": 0,
    "interestIncome": 0,
    "interestExpense": 0,
    "depreciationAndAmortization": 6108000,
    "ebitda": 103871000,
    "ebit": 97763000,
    "nonOperatingIncomeExcludingInterest": 0,
    "operatingIncome": 97763000,
    "totalOtherIncomeExpensesNet": 2124000,
    "incomeBeforeTax": 99887000,
    "incomeTaxExpense": 33755000,
    "netIncomeFromContinuingOperations": 66132000,
    "netIncomeFromDiscontinuedOperations": 0,
    "otherAdjustmentsToNetIncome": 0,
    "netIncome": 66132000,
    "netIncomeDeductions": 0,
    "bottomLineNetIncome": 66132000,
    "eps": 0.41,
    "epsDiluted": 0.4,
    "weightedAverageShsOut": 161436000,
    "weightedAverageShsOutDil": 163680000
  },
  {
    "date": "2004-06-30",
    "symbol": "TECH",
    "reportedCurrency": "USD",
    "cik": "0000842023",
    "filingDate": "2004-09-10",
    "acceptedDate": "2004-09-10 16:47:30",
    "fiscalYear": "2004",
    "period": "FY",
    "revenue": 161257000,
    "costOfRevenue": 34887000,
    "grossProfit": 126370000,
    "researchAndDevelopmentExpenses": 20773000,
    "generalAndAdministrativeExpenses": 21725000,
    "sellingAndMarketingExpenses": 0,
    "sellingGeneralAndAdministrativeExpenses": 21725000,
    "otherExpenses": 1599000,
    "operatingExpenses": 44097000,
    "costAndExpenses": 78984000,
    "netInterestIncome": 0,
    "interestIncome": 0,
    "interestExpense": 0,
    "depreciationAndAmortization": 6040000,
    "ebitda": 88313000,
    "ebit": 82273000,
    "nonOperatingIncomeExcludingInterest": 0,
    "operatingIncome": 82273000,
    "totalOtherIncomeExpensesNet": 268000,
    "incomeBeforeTax": 82541000,
    "incomeTaxExpense": 29613000,
    "netIncomeFromContinuingOperations": 52928000,
    "netIncomeFromDiscontinuedOperations": 0,
    "otherAdjustmentsToNetIncome": 0,
    "netIncome": 52928000,
    "netIncomeDeductions": 0,
    "bottomLineNetIncome": 52928000,
    "eps": 0.32,
    "epsDiluted": 0.32,
    "weightedAverageShsOut": 164184000,
    "weightedAverageShsOutDil": 166788000
  },
  {
    "date": "2003-06-30",
    "symbol": "TECH",
    "reportedCurrency": "USD",
    "cik": "0000842023",
    "filingDate": "2003-09-26",
    "acceptedDate": "2003-09-26 10:37:58",
    "fiscalYear": "2003",
    "period": "FY",
    "revenue": 145010900,
    "costOfRevenue": 35396174,
    "grossProfit": 109614726,
    "researchAndDevelopmentExpenses": 20581343,
    "generalAndAdministrativeExpenses": 19376538,
    "sellingAndMarketingExpenses": 0,
    "sellingGeneralAndAdministrativeExpenses": 19376538,
    "otherExpenses": 1939250,
    "operatingExpenses": 41897131,
    "costAndExpenses": 77293305,
    "netInterestIncome": 0,
    "interestIncome": 0,
    "interestExpense": 0,
    "depreciationAndAmortization": 6352847,
    "ebitda": 74071000,
    "ebit": 67718000,
    "nonOperatingIncomeExcludingInterest": -405,
    "operatingIncome": 67717595,
    "totalOtherIncomeExpensesNet": 1837405,
    "incomeBeforeTax": 69555293,
    "incomeTaxExpense": 24159000,
    "netIncomeFromContinuingOperations": 45396000,
    "netIncomeFromDiscontinuedOperations": 0,
    "otherAdjustmentsToNetIncome": 0,
    "netIncome": 45396293,
    "netIncomeDeductions": 0,
    "bottomLineNetIncome": 45396000,
    "eps": 0.27,
    "epsDiluted": 0.27,
    "weightedAverageShsOut": 165476236,
    "weightedAverageShsOutDil": 168124000
  },
  {
    "date": "2002-06-30",
    "symbol": "TECH",
    "reportedCurrency": "USD",
    "cik": "0000842023",
    "filingDate": "2002-09-27",
    "acceptedDate": "2002-09-27 10:13:12",
    "fiscalYear": "2002",
    "period": "FY",
    "revenue": 130900395,
    "costOfRevenue": 32507846,
    "grossProfit": 98392549,
    "researchAndDevelopmentExpenses": 17470267,
    "generalAndAdministrativeExpenses": 19554195,
    "sellingAndMarketingExpenses": 0,
    "sellingGeneralAndAdministrativeExpenses": 19554195,
    "otherExpenses": 8549246,
    "operatingExpenses": 45573708,
    "costAndExpenses": 78081554,
    "netInterestIncome": 0,
    "interestIncome": 0,
    "interestExpense": 0,
    "depreciationAndAmortization": 12687915,
    "ebitda": 65506756,
    "ebit": 52818841,
    "nonOperatingIncomeExcludingInterest": 0,
    "operatingIncome": 52818841,
    "totalOtherIncomeExpensesNet": -15083172,
    "incomeBeforeTax": 37735669,
    "incomeTaxExpense": 10606000,
    "netIncomeFromContinuingOperations": 27129669,
    "netIncomeFromDiscontinuedOperations": 0,
    "otherAdjustmentsToNetIncome": 0,
    "netIncome": 27129669,
    "netIncomeDeductions": 0,
    "bottomLineNetIncome": 27129669,
    "eps": 0.16,
    "epsDiluted": 0.16,
    "weightedAverageShsOut": 166030908,
    "weightedAverageShsOutDil": 170090656
  },
  {
    "date": "2001-06-30",
    "symbol": "TECH",
    "reportedCurrency": "USD",
    "cik": "0000842023",
    "filingDate": "2001-09-27",
    "acceptedDate": "2001-09-27 00:00:00",
    "fiscalYear": "2001",
    "period": "FY",
    "revenue": 115356562,
    "costOfRevenue": 28424906,
    "grossProfit": 86931656,
    "researchAndDevelopmentExpenses": 14522233,
    "generalAndAdministrativeExpenses": 17714215,
    "sellingAndMarketingExpenses": 0,
    "sellingGeneralAndAdministrativeExpenses": 17714215,
    "otherExpenses": 8889254,
    "operatingExpenses": 41125702,
    "costAndExpenses": 69550608,
    "netInterestIncome": 0,
    "interestIncome": 0,
    "interestExpense": 0,
    "depreciationAndAmortization": 12737448,
    "ebitda": 58543402,
    "ebit": 45805954,
    "nonOperatingIncomeExcludingInterest": 0,
    "operatingIncome": 45805954,
    "totalOtherIncomeExpensesNet": 2002422,
    "incomeBeforeTax": 47808376,
    "incomeTaxExpense": 13763000,
    "netIncomeFromContinuingOperations": 34045376,
    "netIncomeFromDiscontinuedOperations": 0,
    "otherAdjustmentsToNetIncome": 0,
    "netIncome": 34045376,
    "netIncomeDeductions": 0,
    "bottomLineNetIncome": 34045376,
    "eps": 0.21,
    "epsDiluted": 0.2,
    "weightedAverageShsOut": 165754680,
    "weightedAverageShsOutDil": 170672944
  },
  {
    "date": "2000-06-30",
    "symbol": "TECH",
    "reportedCurrency": "USD",
    "cik": "0000842023",
    "filingDate": "2000-09-27",
    "acceptedDate": "2000-09-27 00:00:00",
    "fiscalYear": "2000",
    "period": "FY",
    "revenue": 103838155,
    "costOfRevenue": 23328550,
    "grossProfit": 80509605,
    "researchAndDevelopmentExpenses": 11198309,
    "generalAndAdministrativeExpenses": 17315131,
    "sellingAndMarketingExpenses": 0,
    "sellingGeneralAndAdministrativeExpenses": 17315131,
    "otherExpenses": 12651350,
    "operatingExpenses": 41164790,
    "costAndExpenses": 64493340,
    "netInterestIncome": 0,
    "interestIncome": 0,
    "interestExpense": 0,
    "depreciationAndAmortization": 12651350,
    "ebitda": 51996165,
    "ebit": 39344815,
    "nonOperatingIncomeExcludingInterest": 0,
    "operatingIncome": 39344815,
    "totalOtherIncomeExpensesNet": 66982,
    "incomeBeforeTax": 39411797,
    "incomeTaxExpense": 12829000,
    "netIncomeFromContinuingOperations": 26582797,
    "netIncomeFromDiscontinuedOperations": 0,
    "otherAdjustmentsToNetIncome": 0,
    "netIncome": 26582797,
    "netIncomeDeductions": 0,
    "bottomLineNetIncome": 26582797,
    "eps": 0.16,
    "epsDiluted": 0.16,
    "weightedAverageShsOut": 162501928,
    "weightedAverageShsOutDil": 168824168
  },
  {
    "date": "1999-06-30",
    "symbol": "TECH",
    "reportedCurrency": "USD",
    "cik": "0000842023",
    "filingDate": "1999-09-27",
    "acceptedDate": "1999-09-27 00:00:00",
    "fiscalYear": "1999",
    "period": "FY",
    "revenue": 90900000,
    "costOfRevenue": 25000000,
    "grossProfit": 65900000,
    "researchAndDevelopmentExpenses": 12000000,
    "generalAndAdministrativeExpenses": 16900000,
    "sellingAndMarketingExpenses": 0,
    "sellingGeneralAndAdministrativeExpenses": 16900000,
    "otherExpenses": 11900000,
    "operatingExpenses": 40800000,
    "costAndExpenses": 65800000,
    "netInterestIncome": 0,
    "interestIncome": 0,
    "interestExpense": 0,
    "depreciationAndAmortization": 11900000,
    "ebitda": 37000000,
    "ebit": 25100000,
    "nonOperatingIncomeExcludingInterest": 0,
    "operatingIncome": 25100000,
    "totalOtherIncomeExpensesNet": 1000000,
    "incomeBeforeTax": 26100000,
    "incomeTaxExpense": 9400000,
    "netIncomeFromContinuingOperations": 16700000,
    "netIncomeFromDiscontinuedOperations": 0,
    "otherAdjustmentsToNetIncome": 0,
    "netIncome": 16700000,
    "netIncomeDeductions": 0,
    "bottomLineNetIncome": 16700000,
    "eps": 0.1,
    "epsDiluted": 0.1,
    "weightedAverageShsOut": 160938936,
    "weightedAverageShsOutDil": 165493400
  },
  {
    "date": "1998-06-30",
    "symbol": "TECH",
    "reportedCurrency": "USD",
    "cik": "0000842023",
    "filingDate": "1998-09-14",
    "acceptedDate": "1998-09-14 00:00:00",
    "fiscalYear": "1998",
    "period": "FY",
    "revenue": 67300000,
    "costOfRevenue": 17800000,
    "grossProfit": 49500000,
    "researchAndDevelopmentExpenses": 10600000,
    "generalAndAdministrativeExpenses": 15400000,
    "sellingAndMarketingExpenses": 0,
    "sellingGeneralAndAdministrativeExpenses": 15400000,
    "otherExpenses": 2300000,
    "operatingExpenses": 28300000,
    "costAndExpenses": 46100000,
    "netInterestIncome": 0,
    "interestIncome": 0,
    "interestExpense": 0,
    "depreciationAndAmortization": 2300000,
    "ebitda": 23500000,
    "ebit": 21200000,
    "nonOperatingIncomeExcludingInterest": 0,
    "operatingIncome": 21200000,
    "totalOtherIncomeExpensesNet": 1200000,
    "incomeBeforeTax": 22400000,
    "incomeTaxExpense": 7200000,
    "netIncomeFromContinuingOperations": 15200000,
    "netIncomeFromDiscontinuedOperations": 0,
    "otherAdjustmentsToNetIncome": 0,
    "netIncome": 15200000,
    "netIncomeDeductions": 0,
    "bottomLineNetIncome": 15200000,
    "eps": 0.1,
    "epsDiluted": 0.0969,
    "weightedAverageShsOut": 151623744,
    "weightedAverageShsOutDil": 156861040
  },
  {
    "date": "1997-06-30",
    "symbol": "TECH",
    "reportedCurrency": "USD",
    "cik": "0000842023",
    "filingDate": "1997-09-26",
    "acceptedDate": "1997-09-26 00:00:00",
    "fiscalYear": "1997",
    "period": "FY",
    "revenue": 60900000,
    "costOfRevenue": 17000000,
    "grossProfit": 43900000,
    "researchAndDevelopmentExpenses": 11700000,
    "generalAndAdministrativeExpenses": 14600000,
    "sellingAndMarketingExpenses": 0,
    "sellingGeneralAndAdministrativeExpenses": 14600000,
    "otherExpenses": 2300000,
    "operatingExpenses": 28600000,
    "costAndExpenses": 45600000,
    "netInterestIncome": 0,
    "interestIncome": 0,
    "interestExpense": 0,
    "depreciationAndAmortization": 2300000,
    "ebitda": 17600000,
    "ebit": 15300000,
    "nonOperatingIncomeExcludingInterest": 0,
    "operatingIncome": 15300000,
    "totalOtherIncomeExpensesNet": 700000,
    "incomeBeforeTax": 16000000,
    "incomeTaxExpense": 5100000,
    "netIncomeFromContinuingOperations": 10900000,
    "netIncomeFromDiscontinuedOperations": 0,
    "otherAdjustmentsToNetIncome": 0,
    "netIncome": 10900000,
    "netIncomeDeductions": 0,
    "bottomLineNetIncome": 10900000,
    "eps": 0.0725,
    "epsDiluted": 0.07,
    "weightedAverageShsOut": 150344828,
    "weightedAverageShsOutDil": 155714286
  },
  {
    "date": "1996-06-30",
    "symbol": "TECH",
    "reportedCurrency": "USD",
    "cik": "0000842023",
    "filingDate": "1996-09-27",
    "acceptedDate": "1996-09-27 00:00:00",
    "fiscalYear": "1996",
    "period": "FY",
    "revenue": 54600000,
    "costOfRevenue": 17100000,
    "grossProfit": 37500000,
    "researchAndDevelopmentExpenses": 10400000,
    "generalAndAdministrativeExpenses": 13000000,
    "sellingAndMarketingExpenses": 0,
    "sellingGeneralAndAdministrativeExpenses": 13000000,
    "otherExpenses": 1900000,
    "operatingExpenses": 25300000,
    "costAndExpenses": 42400000,
    "netInterestIncome": 0,
    "interestIncome": 0,
    "interestExpense": 0,
    "depreciationAndAmortization": 1900000,
    "ebitda": 14100000,
    "ebit": 12200000,
    "nonOperatingIncomeExcludingInterest": 0,
    "operatingIncome": 12200000,
    "totalOtherIncomeExpensesNet": 400000,
    "incomeBeforeTax": 12600000,
    "incomeTaxExpense": 4000000,
    "netIncomeFromContinuingOperations": 8600000,
    "netIncomeFromDiscontinuedOperations": 0,
    "otherAdjustmentsToNetIncome": 0,
    "netIncome": 8600000,
    "netIncomeDeductions": 0,
    "bottomLineNetIncome": 8600000,
    "eps": 0.0553,
    "epsDiluted": 0.0553,
    "weightedAverageShsOut": 155542800,
    "weightedAverageShsOutDil": 155542800
  }
]