[
  {
    "symbol": "BKE",
    "date": "2026-01-31",
    "fiscalYear": "2025",
    "period": "FY",
    "reportedCurrency": "USD",
    "growthRevenue": 0.06581811940487267,
    "growthCostOfRevenue": 0.05932930283468448,
    "growthGrossProfit": 0.07265847597872423,
    "growthGrossProfitRatio": 0.006417939806477971,
    "growthResearchAndDevelopmentExpenses": 0,
    "growthGeneralAndAdministrativeExpenses": 0.1320411351657596,
    "growthSellingAndMarketingExpenses": 0.05218708216225066,
    "growthOtherExpenses": 0,
    "growthOperatingExpenses": 0.06542258190272122,
    "growthCostAndExpenses": 0.06152254628325609,
    "growthInterestIncome": 0,
    "growthInterestExpense": 0,
    "growthDepreciationAndAmortization": -1,
    "growthEBITDA": -0.007787594498588214,
    "growthOperatingIncome": 0.08319384829552046,
    "growthIncomeBeforeTax": 0.07115452503520485,
    "growthIncomeTaxExpense": 0.0652554205652474,
    "growthNetIncome": 0.07303497247631326,
    "growthEPS": 0.06377551020408163,
    "growthEPSDiluted": 0.06426735218508986,
    "growthWeightedAverageShsOut": 0.0069308120668242455,
    "growthWeightedAverageShsOutDil": 0.007771814748558935,
    "growthEBIT": 0.08319384829552046,
    "growthNonOperatingIncomeExcludingInterest": 0,
    "growthNetInterestIncome": 0,
    "growthTotalOtherIncomeExpensesNet": -0.10589167123621519,
    "growthNetIncomeFromContinuingOperations": 0.07303497247631326,
    "growthOtherAdjustmentsToNetIncome": 0,
    "growthNetIncomeDeductions": 0
  },
  {
    "symbol": "BKE",
    "date": "2025-02-01",
    "fiscalYear": "2024",
    "period": "FY",
    "reportedCurrency": "USD",
    "growthRevenue": -0.034424653993094925,
    "growthCostOfRevenue": -0.026688493030775483,
    "growthGrossProfit": -0.04244788511707171,
    "growthGrossProfitRatio": -0.008309275011406391,
    "growthResearchAndDevelopmentExpenses": 0,
    "growthGeneralAndAdministrativeExpenses": 0.022092370323576895,
    "growthSellingAndMarketingExpenses": 0.007415348878763513,
    "growthOtherExpenses": 0,
    "growthOperatingExpenses": 0.009818796227651248,
    "growthCostAndExpenses": -0.01385596383187397,
    "growthInterestIncome": 0,
    "growthInterestExpense": 0,
    "growthDepreciationAndAmortization": 0.06250600096015363,
    "growthEBITDA": -0.09727327854081518,
    "growthOperatingIncome": -0.10955179499666125,
    "growthIncomeBeforeTax": -0.108701139290839,
    "growthIncomeTaxExpense": -0.10082833063957515,
    "growthNetIncome": -0.11118184422446446,
    "growthEPS": -0.11711711711711721,
    "growthEPSDiluted": -0.11590909090909095,
    "growthWeightedAverageShsOut": 0.0068573272558589814,
    "growthWeightedAverageShsOutDil": 0.007106395756180562,
    "growthEBIT": -0.10955179499666125,
    "growthNonOperatingIncomeExcludingInterest": 0,
    "growthNetInterestIncome": 0,
    "growthTotalOtherIncomeExpensesNet": -0.09600132187706543,
    "growthNetIncomeFromContinuingOperations": -0.11118184422446446,
    "growthOtherAdjustmentsToNetIncome": 0,
    "growthNetIncomeDeductions": 0
  },
  {
    "symbol": "BKE",
    "date": "2024-02-03",
    "fiscalYear": "2023",
    "period": "FY",
    "reportedCurrency": "USD",
    "growthRevenue": -0.06250803791591801,
    "growthCostOfRevenue": -0.04056731780795715,
    "growthGrossProfit": -0.08422743686048731,
    "growthGrossProfitRatio": -0.023167557397986125,
    "growthResearchAndDevelopmentExpenses": 0,
    "growthGeneralAndAdministrativeExpenses": 0.05572434234901816,
    "growthSellingAndMarketingExpenses": -0.0097757331799885,
    "growthOtherExpenses": 0,
    "growthOperatingExpenses": 0.0003880748898298507,
    "growthCostAndExpenses": -0.026559035647039736,
    "growthInterestIncome": -1,
    "growthInterestExpense": 0,
    "growthDepreciationAndAmortization": 0.10474675152479448,
    "growthEBITDA": -0.15878981056927205,
    "growthOperatingIncome": -0.17393305133300013,
    "growthIncomeBeforeTax": -0.13681593524664534,
    "growthIncomeTaxExpense": -0.13843093373119483,
    "growthNetIncome": -0.13630579752264105,
    "growthEPS": -0.1411992263056092,
    "growthEPSDiluted": -0.1423001949317738,
    "growthWeightedAverageShsOut": 0.006352879092329863,
    "growthWeightedAverageShsOutDil": 0.00652817795329532,
    "growthEBIT": -0.17393305133300013,
    "growthNonOperatingIncomeExcludingInterest": 0,
    "growthNetInterestIncome": -1,
    "growthTotalOtherIncomeExpensesNet": 1.6221837088388216,
    "growthNetIncomeFromContinuingOperations": -0.13630579752264105,
    "growthOtherAdjustmentsToNetIncome": 0,
    "growthNetIncomeDeductions": 0
  },
  {
    "symbol": "BKE",
    "date": "2023-01-28",
    "fiscalYear": "2022",
    "period": "FY",
    "reportedCurrency": "USD",
    "growthRevenue": 0.03906977175312663,
    "growthCostOfRevenue": 0.0429957699369387,
    "growthGrossProfit": 0.03521237838988436,
    "growthGrossProfitRatio": -0.0037123527649426087,
    "growthResearchAndDevelopmentExpenses": 0,
    "growthGeneralAndAdministrativeExpenses": 0.05664957131112242,
    "growthSellingAndMarketingExpenses": 0.10309506651052458,
    "growthOtherExpenses": 0,
    "growthOperatingExpenses": 0.09562218512802746,
    "growthCostAndExpenses": 0.06041759634994182,
    "growthInterestIncome": 2.0691489361702127,
    "growthInterestExpense": 0,
    "growthDepreciationAndAmortization": 0.00888223018888116,
    "growthEBITDA": -0.02033101064971145,
    "growthOperatingIncome": -0.0219583366865475,
    "growthIncomeBeforeTax": -0.007990999393051175,
    "growthIncomeTaxExpense": -0.030204376921685656,
    "growthNetIncome": -0.0007613217172906365,
    "growthEPS": -0.005769230769230817,
    "growthEPSDiluted": -0.005813953488372141,
    "growthWeightedAverageShsOut": 0.005612932195779075,
    "growthWeightedAverageShsOutDil": 0.004981269616280247,
    "growthEBIT": -0.0219583366865475,
    "growthNonOperatingIncomeExcludingInterest": 0,
    "growthNetInterestIncome": 2.0691489361702127,
    "growthTotalOtherIncomeExpensesNet": 2.0691489361702127,
    "growthNetIncomeFromContinuingOperations": -0.0007613217172906365,
    "growthOtherAdjustmentsToNetIncome": 0,
    "growthNetIncomeDeductions": 0
  },
  {
    "symbol": "BKE",
    "date": "2022-01-29",
    "fiscalYear": "2021",
    "period": "FY",
    "reportedCurrency": "USD",
    "growthRevenue": 0.4364125164488648,
    "growthCostOfRevenue": 0.28163240846167675,
    "growthGrossProfit": 0.6298007327762637,
    "growthGrossProfitRatio": 0.13463278428125164,
    "growthResearchAndDevelopmentExpenses": 0,
    "growthGeneralAndAdministrativeExpenses": 0.23134400308522945,
    "growthSellingAndMarketingExpenses": 0.3937371179861685,
    "growthOtherExpenses": 0,
    "growthOperatingExpenses": 0.36477738710315244,
    "growthCostAndExpenses": 0.3080124813162115,
    "growthInterestIncome": -0.2287179487179487,
    "growthInterestExpense": 0,
    "growthDepreciationAndAmortization": -0.10420361405358769,
    "growthEBITDA": 0.8751515472377372,
    "growthOperatingIncome": 0.9967563771410887,
    "growthIncomeBeforeTax": 0.9757878172766998,
    "growthIncomeTaxExpense": 1.0323220937071163,
    "growthNetIncome": 0.9580602279101575,
    "growthEPS": 0.9475655430711611,
    "growthEPSDiluted": 0.9398496240601504,
    "growthWeightedAverageShsOut": 0.00490206132704338,
    "growthWeightedAverageShsOutDil": 0.00758982310815498,
    "growthEBIT": 0.9967563771410887,
    "growthNonOperatingIncomeExcludingInterest": 0,
    "growthNetInterestIncome": -0.2287179487179487,
    "growthTotalOtherIncomeExpensesNet": -0.2287179487179487,
    "growthNetIncomeFromContinuingOperations": 0.9580602279101575,
    "growthOtherAdjustmentsToNetIncome": 0,
    "growthNetIncomeDeductions": 0
  },
  {
    "symbol": "BKE",
    "date": "2021-01-30",
    "fiscalYear": "2020",
    "period": "FY",
    "reportedCurrency": "USD",
    "growthRevenue": 0.0011374567622026673,
    "growthCostOfRevenue": -0.04240789624698726,
    "growthGrossProfit": 0.06144529159624239,
    "growthGrossProfitRatio": 0.06023931511841738,
    "growthResearchAndDevelopmentExpenses": 0,
    "growthGeneralAndAdministrativeExpenses": -0.00021688314817938645,
    "growthSellingAndMarketingExpenses": -0.06515062597809076,
    "growthOtherExpenses": 0,
    "growthOperatingExpenses": -0.054196124027856264,
    "growthCostAndExpenses": -0.046179742103161336,
    "growthInterestIncome": -0.5289855072463768,
    "growthInterestExpense": 0,
    "growthDepreciationAndAmortization": -0.12299802429694397,
    "growthEBITDA": 0.2163685071416612,
    "growthOperatingIncome": 0.2777629907906644,
    "growthIncomeBeforeTax": 0.2413820648187819,
    "growthIncomeTaxExpense": 0.22627561752509165,
    "growthNetIncome": 0.24619598004385754,
    "growthEPS": 0.2418604651162791,
    "growthEPSDiluted": 0.24299065420560748,
    "growthWeightedAverageShsOut": 0.00345771502665322,
    "growthWeightedAverageShsOutDil": 0.00409726917009813,
    "growthEBIT": 0.2777629907906644,
    "growthNonOperatingIncomeExcludingInterest": 0,
    "growthNetInterestIncome": -0.5289855072463768,
    "growthTotalOtherIncomeExpensesNet": -0.5289855072463768,
    "growthNetIncomeFromContinuingOperations": 0.24619598004385754,
    "growthOtherAdjustmentsToNetIncome": 0,
    "growthNetIncomeDeductions": 0
  },
  {
    "symbol": "BKE",
    "date": "2020-02-01",
    "fiscalYear": "2019",
    "period": "FY",
    "reportedCurrency": "USD",
    "growthRevenue": 0.016666365517179073,
    "growthCostOfRevenue": 0.006462940609098943,
    "growthGrossProfit": 0.031144061430370445,
    "growthGrossProfitRatio": 0.014240360933755376,
    "growthResearchAndDevelopmentExpenses": 0,
    "growthGeneralAndAdministrativeExpenses": -0.03748289379073597,
    "growthSellingAndMarketingExpenses": 0.012116892373485389,
    "growthOtherExpenses": 0,
    "growthOperatingExpenses": 0.0033939097268963266,
    "growthCostAndExpenses": 0.0054789109667158446,
    "growthInterestIncome": 0,
    "growthInterestExpense": 0,
    "growthDepreciationAndAmortization": -0.11393772348033374,
    "growthEBITDA": 0.050820160242529236,
    "growthOperatingIncome": 0.39771471088435373,
    "growthIncomeBeforeTax": 0.08735510565048482,
    "growthIncomeTaxExpense": 0.0722386905529063,
    "growthNetIncome": 0.09226215379466153,
    "growthEPS": 0.09137055837563449,
    "growthEPSDiluted": 0.0862944162436549,
    "growthWeightedAverageShsOut": 0.0035940759713300146,
    "growthWeightedAverageShsOutDil": 0.004093471016579586,
    "growthEBIT": 0.0873991135220958,
    "growthNonOperatingIncomeExcludingInterest": 0,
    "growthNetInterestIncome": 0,
    "growthTotalOtherIncomeExpensesNet": 0.08642407277816655,
    "growthNetIncomeFromContinuingOperations": 0.09226215379466153,
    "growthOtherAdjustmentsToNetIncome": 0,
    "growthNetIncomeDeductions": 0
  },
  {
    "symbol": "BKE",
    "date": "2019-01-31",
    "fiscalYear": "2018",
    "period": "FY",
    "reportedCurrency": "USD",
    "growthRevenue": -0.03052836716372156,
    "growthCostOfRevenue": -0.026125090699100226,
    "growthGrossProfit": -0.03670830449735937,
    "growthGrossProfitRatio": -0.006374541709879106,
    "growthResearchAndDevelopmentExpenses": 0,
    "growthGeneralAndAdministrativeExpenses": 0.08114953481957018,
    "growthSellingAndMarketingExpenses": -0.019585767804802298,
    "growthOtherExpenses": 0,
    "growthOperatingExpenses": -0.003252759763361727,
    "growthCostAndExpenses": -0.01890666262886532,
    "growthInterestIncome": 0,
    "growthInterestExpense": 0,
    "growthDepreciationAndAmortization": -0.12675231744999188,
    "growthEBITDA": -0.10342609951281072,
    "growthOperatingIncome": -0.2983188890049076,
    "growthIncomeBeforeTax": -0.09206007814460336,
    "growthIncomeTaxExpense": -0.3765117120012857,
    "growthNetIncome": 0.06578081977995029,
    "growthEPS": 0.059139784946236486,
    "growthEPSDiluted": 0.0648648648648648,
    "growthWeightedAverageShsOut": 0.003378238341968912,
    "growthWeightedAverageShsOutDil": 0.004982118123746718,
    "growthEBIT": -0.09807723862229449,
    "growthNonOperatingIncomeExcludingInterest": 0,
    "growthNetInterestIncome": 0,
    "growthTotalOtherIncomeExpensesNet": 0.057148141298316996,
    "growthNetIncomeFromContinuingOperations": 0.06578081977995029,
    "growthOtherAdjustmentsToNetIncome": 0,
    "growthNetIncomeDeductions": 0
  },
  {
    "symbol": "BKE",
    "date": "2018-01-31",
    "fiscalYear": "2017",
    "period": "FY",
    "reportedCurrency": "USD",
    "growthRevenue": -0.06307795989836625,
    "growthCostOfRevenue": -0.07676582338736898,
    "growthGrossProfit": -0.04316813036296983,
    "growthGrossProfitRatio": 0.021250252040438358,
    "growthResearchAndDevelopmentExpenses": 0,
    "growthGeneralAndAdministrativeExpenses": 0.036439246263807665,
    "growthSellingAndMarketingExpenses": 0.0006555530196714466,
    "growthOtherExpenses": 0,
    "growthOperatingExpenses": 0.006288664855487546,
    "growthCostAndExpenses": -0.052074349876476834,
    "growthInterestIncome": 0,
    "growthInterestExpense": 0,
    "growthDepreciationAndAmortization": -0.06228078201726294,
    "growthEBITDA": -0.11169137738686155,
    "growthOperatingIncome": -0.12229641267347473,
    "growthIncomeBeforeTax": -0.10741596329453322,
    "growthIncomeTaxExpense": -0.14632138569713599,
    "growthNetIncome": -0.08425802104919304,
    "growthEPS": -0.08823529411764702,
    "growthEPSDiluted": -0.08866995073891612,
    "growthWeightedAverageShsOut": 0.0025974025974025974,
    "growthWeightedAverageShsOutDil": 0.0024245689655172415,
    "growthEBIT": -0.12229641267347473,
    "growthNonOperatingIncomeExcludingInterest": 0,
    "growthNetInterestIncome": 0,
    "growthTotalOtherIncomeExpensesNet": 0.5400170891483907,
    "growthNetIncomeFromContinuingOperations": -0.08425802104919304,
    "growthOtherAdjustmentsToNetIncome": 0,
    "growthNetIncomeDeductions": 0
  },
  {
    "symbol": "BKE",
    "date": "2017-01-31",
    "fiscalYear": "2016",
    "period": "FY",
    "reportedCurrency": "USD",
    "growthRevenue": -0.12927914570709959,
    "growthCostOfRevenue": -0.09481130966837194,
    "growthGrossProfit": -0.17497470923408967,
    "growthGrossProfitRatio": -0.052480152721891764,
    "growthResearchAndDevelopmentExpenses": 0,
    "growthGeneralAndAdministrativeExpenses": -0.02054376050099282,
    "growthSellingAndMarketingExpenses": -0.03104488286414688,
    "growthOtherExpenses": 0,
    "growthOperatingExpenses": -0.02940674230480555,
    "growthCostAndExpenses": -0.07630658810734044,
    "growthInterestIncome": 0,
    "growthInterestExpense": 0,
    "growthDepreciationAndAmortization": 0.020067201792047788,
    "growthEBITDA": -0.2910747717113055,
    "growthOperatingIncome": -0.3346342143317595,
    "growthIncomeBeforeTax": -0.3345186181991619,
    "growthIncomeTaxExpense": -0.3339121097542866,
    "growthNetIncome": -0.33487911028428263,
    "growthEPS": -0.3333333333333333,
    "growthEPSDiluted": -0.33660130718954256,
    "growthWeightedAverageShsOut": 0.0009567586680255413,
    "growthWeightedAverageShsOutDil": 0.0010787486515641855,
    "growthEBIT": -0.3346342143317595,
    "growthNonOperatingIncomeExcludingInterest": 0,
    "growthNetInterestIncome": 0,
    "growthTotalOtherIncomeExpensesNet": -0.329449961802903,
    "growthNetIncomeFromContinuingOperations": -0.33487911028428263,
    "growthOtherAdjustmentsToNetIncome": 0,
    "growthNetIncomeDeductions": 0
  },
  {
    "symbol": "BKE",
    "date": "2016-01-31",
    "fiscalYear": "2015",
    "period": "FY",
    "reportedCurrency": "USD",
    "growthRevenue": -0.029073609321315155,
    "growthCostOfRevenue": -0.01176042489277032,
    "growthGrossProfit": -0.05111248649799342,
    "growthGrossProfitRatio": -0.022698813780163717,
    "growthResearchAndDevelopmentExpenses": 0,
    "growthGeneralAndAdministrativeExpenses": 0.04276499163813013,
    "growthSellingAndMarketingExpenses": -0.0007381704656586174,
    "growthOtherExpenses": 0,
    "growthOperatingExpenses": 0.005807660199952868,
    "growthCostAndExpenses": -0.006852502150821999,
    "growthInterestIncome": 0,
    "growthInterestExpense": 0,
    "growthDepreciationAndAmortization": 0.014615360333343855,
    "growthEBITDA": -0.09326801823649239,
    "growthOperatingIncome": -0.10656761605304838,
    "growthIncomeBeforeTax": -0.09577351980777525,
    "growthIncomeTaxExpense": -0.09874191821438867,
    "growthNetIncome": -0.09399990157722497,
    "growthEPS": -0.09734513274336284,
    "growthEPSDiluted": -0.09467455621301771,
    "growthWeightedAverageShsOut": 0.003171489974335969,
    "growthWeightedAverageShsOutDil": 0.0023705552089831566,
    "growthEBIT": -0.10656761605304838,
    "growthNonOperatingIncomeExcludingInterest": 0,
    "growthNetInterestIncome": 0,
    "growthTotalOtherIncomeExpensesNet": 0.922879177377892,
    "growthNetIncomeFromContinuingOperations": -0.09399990157722497,
    "growthOtherAdjustmentsToNetIncome": 0,
    "growthNetIncomeDeductions": 0
  },
  {
    "symbol": "BKE",
    "date": "2015-01-31",
    "fiscalYear": "2014",
    "period": "FY",
    "reportedCurrency": "USD",
    "growthRevenue": 0.02228810080842127,
    "growthCostOfRevenue": 0.026960067169590495,
    "growthGrossProfit": 0.016402047501227097,
    "growthGrossProfitRatio": -0.00575772437755074,
    "growthResearchAndDevelopmentExpenses": 0,
    "growthGeneralAndAdministrativeExpenses": 0.0684383685971978,
    "growthSellingAndMarketingExpenses": 0.02800964749894873,
    "growthOtherExpenses": 0,
    "growthOperatingExpenses": 0.03389620526035408,
    "growthCostAndExpenses": 0.028888401585750748,
    "growthInterestIncome": 0,
    "growthInterestExpense": 0,
    "growthDepreciationAndAmortization": -0.029174711164230333,
    "growthEBITDA": -0.0033595166163141992,
    "growthOperatingIncome": -0.00008171396997595274,
    "growthIncomeBeforeTax": -0.002917959271431643,
    "growthIncomeTaxExpense": -0.007560895863985614,
    "growthNetIncome": -0.00012301333464547558,
    "growthEPS": -0.005865102639296193,
    "growthEPSDiluted": -0.0029498525073746993,
    "growthWeightedAverageShsOut": 0.0038329423592493297,
    "growthWeightedAverageShsOutDil": 0.0023761880940470236,
    "growthEBIT": -0.00008171396997595274,
    "growthNonOperatingIncomeExcludingInterest": 0,
    "growthNetInterestIncome": -1,
    "growthTotalOtherIncomeExpensesNet": -0.21346042749855576,
    "growthNetIncomeFromContinuingOperations": -0.00012301333464547558,
    "growthOtherAdjustmentsToNetIncome": 0,
    "growthNetIncomeDeductions": 0
  },
  {
    "symbol": "BKE",
    "date": "2014-01-31",
    "fiscalYear": "2013",
    "period": "FY",
    "reportedCurrency": "USD",
    "growthRevenue": 0.003553358653460343,
    "growthCostOfRevenue": 0.00666568484949383,
    "growthGrossProfit": -0.0003404664390214594,
    "growthGrossProfitRatio": -0.0038800379923662988,
    "growthResearchAndDevelopmentExpenses": 0,
    "growthGeneralAndAdministrativeExpenses": -0.10003318273476784,
    "growthSellingAndMarketingExpenses": 0.024410411808103466,
    "growthOtherExpenses": 0,
    "growthOperatingExpenses": 0.004192585220204031,
    "growthCostAndExpenses": 0.005976910070313871,
    "growthInterestIncome": 0,
    "growthInterestExpense": 0,
    "growthDepreciationAndAmortization": -0.03555594963646037,
    "growthEBITDA": -0.008164131927440593,
    "growthOperatingIncome": -0.004574416577902586,
    "growthIncomeBeforeTax": -0.004749731561832487,
    "growthIncomeTaxExpense": 0.004907899870628581,
    "growthNetIncome": -0.01047442256778552,
    "growthEPS": -0.017291066282420765,
    "growthEPSDiluted": -0.01453488372093018,
    "growthWeightedAverageShsOut": 0.007618766224173227,
    "growthWeightedAverageShsOutDil": 0.005575351079438273,
    "growthEBIT": -0.017978670151586364,
    "growthNonOperatingIncomeExcludingInterest": 1,
    "growthNetInterestIncome": -0.06072644721906924,
    "growthTotalOtherIncomeExpensesNet": -0.017593643586833144,
    "growthNetIncomeFromContinuingOperations": -0.01047442256778552,
    "growthOtherAdjustmentsToNetIncome": 0,
    "growthNetIncomeDeductions": 0
  },
  {
    "symbol": "BKE",
    "date": "2013-01-31",
    "fiscalYear": "2012",
    "period": "FY",
    "reportedCurrency": "USD",
    "growthRevenue": 0.05744506306058821,
    "growthCostOfRevenue": 0.051155073861121905,
    "growthGrossProfit": 0.06542125870843157,
    "growthGrossProfitRatio": 0.0075428937109588475,
    "growthResearchAndDevelopmentExpenses": 0,
    "growthGeneralAndAdministrativeExpenses": 0.057665829756216085,
    "growthSellingAndMarketingExpenses": 0.03414851454729792,
    "growthOtherExpenses": 0,
    "growthOperatingExpenses": 0.03789786299954807,
    "growthCostAndExpenses": 0.04742894610138079,
    "growthInterestIncome": 0,
    "growthInterestExpense": 0,
    "growthDepreciationAndAmortization": 0.03250022887485123,
    "growthEBITDA": 0.08517627996685112,
    "growthOperatingIncome": 0.09248053486797563,
    "growthIncomeBeforeTax": 0.08823150269667875,
    "growthIncomeTaxExpense": 0.09400730131985398,
    "growthNetIncome": 0.08483652017747728,
    "growthEPS": 0.07430340557275548,
    "growthEPSDiluted": 0.07499999999999993,
    "growthWeightedAverageShsOut": 0.011182483621075994,
    "growthWeightedAverageShsOutDil": 0.007411474059840791,
    "growthEBIT": 0.10739251861882193,
    "growthNonOperatingIncomeExcludingInterest": 0,
    "growthNetInterestIncome": -0.15308799641624524,
    "growthTotalOtherIncomeExpensesNet": -0.15308819995193462,
    "growthNetIncomeFromContinuingOperations": 0.08483652017747728,
    "growthOtherAdjustmentsToNetIncome": 0,
    "growthNetIncomeDeductions": 0
  },
  {
    "symbol": "BKE",
    "date": "2012-01-31",
    "fiscalYear": "2011",
    "period": "FY",
    "reportedCurrency": "USD",
    "growthRevenue": 0.11908135913703179,
    "growthCostOfRevenue": 0.11980576926338163,
    "growthGrossProfit": 0.11816409744971118,
    "growthGrossProfitRatio": -0.0008196559702215065,
    "growthResearchAndDevelopmentExpenses": 0,
    "growthGeneralAndAdministrativeExpenses": 0.2045070239334027,
    "growthSellingAndMarketingExpenses": 0.09956646585214797,
    "growthOtherExpenses": 0,
    "growthOperatingExpenses": 0.11505456849137559,
    "growthCostAndExpenses": 0.1184662907893829,
    "growthInterestIncome": 0,
    "growthInterestExpense": 0,
    "growthDepreciationAndAmortization": 0.10033242671501964,
    "growthEBITDA": 0.11864991602507607,
    "growthOperatingIncome": 0.1212381444913103,
    "growthIncomeBeforeTax": 0.1201939649148958,
    "growthIncomeTaxExpense": 0.11286814340717036,
    "growthNetIncome": 0.12454522504863308,
    "growthEPS": 0.10616438356164386,
    "growthEPSDiluted": 0.11888111888111899,
    "growthWeightedAverageShsOut": 0.014637420695927073,
    "growthWeightedAverageShsOutDil": 0.0071026049973418395,
    "growthEBIT": 0.1212381444913103,
    "growthNonOperatingIncomeExcludingInterest": 0,
    "growthNetInterestIncome": 0.06392201482996676,
    "growthTotalOtherIncomeExpensesNet": 0.06392227051904883,
    "growthNetIncomeFromContinuingOperations": 0.12454522504863308,
    "growthOtherAdjustmentsToNetIncome": 0,
    "growthNetIncomeDeductions": 0
  },
  {
    "symbol": "BKE",
    "date": "2011-01-31",
    "fiscalYear": "2010",
    "period": "FY",
    "reportedCurrency": "USD",
    "growthRevenue": 0.05738811760606577,
    "growthCostOfRevenue": 0.06639165065867204,
    "growthGrossProfit": 0.0462035000836206,
    "growthGrossProfitRatio": -0.010577589693044552,
    "growthResearchAndDevelopmentExpenses": 0,
    "growthGeneralAndAdministrativeExpenses": -0.05133267522211254,
    "growthSellingAndMarketingExpenses": 0.05255984022851589,
    "growthOtherExpenses": 0,
    "growthOperatingExpenses": 0.03581779406135506,
    "growthCostAndExpenses": 0.05759095624798769,
    "growthInterestIncome": 0,
    "growthInterestExpense": 0,
    "growthDepreciationAndAmortization": 0.1848418539884623,
    "growthEBITDA": 0.07102053900987101,
    "growthOperatingIncome": 0.05667746237378548,
    "growthIncomeBeforeTax": 0.051688409666531134,
    "growthIncomeTaxExpense": 0.0412891804644382,
    "growthNetIncome": 0.05796406997478457,
    "growthEPS": 0.04659498207885301,
    "growthEPSDiluted": 0.04761904761904758,
    "growthWeightedAverageShsOut": 0.010591041379461257,
    "growthWeightedAverageShsOutDil": 0.007131842713955281,
    "growthEBIT": 0.05667746237378548,
    "growthNonOperatingIncomeExcludingInterest": 0,
    "growthNetInterestIncome": 0.06450734893848667,
    "growthTotalOtherIncomeExpensesNet": -0.16162915326902466,
    "growthNetIncomeFromContinuingOperations": 0.05796406997478457,
    "growthOtherAdjustmentsToNetIncome": 0,
    "growthNetIncomeDeductions": 0
  },
  {
    "symbol": "BKE",
    "date": "2010-01-31",
    "fiscalYear": "2009",
    "period": "FY",
    "reportedCurrency": "USD",
    "growthRevenue": 0.13413488610509997,
    "growthCostOfRevenue": 0.1094841692713094,
    "growthGrossProfit": 0.16632604341345258,
    "growthGrossProfitRatio": 0.028383887814299118,
    "growthResearchAndDevelopmentExpenses": 0,
    "growthGeneralAndAdministrativeExpenses": 0.07905861988615559,
    "growthSellingAndMarketingExpenses": 0.115635599103477,
    "growthOtherExpenses": 0,
    "growthOperatingExpenses": 0.1095746089182093,
    "growthCostAndExpenses": 0.10951020084147019,
    "growthInterestIncome": 0,
    "growthInterestExpense": 0,
    "growthDepreciationAndAmortization": 0.15409339271775563,
    "growthEBITDA": 0.22080173936676178,
    "growthOperatingIncome": 0.22975905694345114,
    "growthIncomeBeforeTax": 0.23812383239925272,
    "growthIncomeTaxExpense": 0.2706793033295291,
    "growthNetIncome": 0.2192722849562777,
    "growthEPS": 0.21304347826086967,
    "growthEPSDiluted": 0.2187499999999999,
    "growthWeightedAverageShsOut": 0.007318094650296471,
    "growthWeightedAverageShsOutDil": 0.002533602439129128,
    "growthEBIT": 0.22975905694345114,
    "growthNonOperatingIncomeExcludingInterest": 0,
    "growthNetInterestIncome": -0.5307191212159919,
    "growthTotalOtherIncomeExpensesNet": 0.7458832335329342,
    "growthNetIncomeFromContinuingOperations": 0.2192722849562777,
    "growthOtherAdjustmentsToNetIncome": 0,
    "growthNetIncomeDeductions": 0
  },
  {
    "symbol": "BKE",
    "date": "2009-01-31",
    "fiscalYear": "2008",
    "period": "FY",
    "reportedCurrency": "USD",
    "growthRevenue": 0.2777243631107555,
    "growthCostOfRevenue": 0.22774873409059807,
    "growthGrossProfit": 0.34945666265940645,
    "growthGrossProfitRatio": 0.056140668213834115,
    "growthResearchAndDevelopmentExpenses": 0,
    "growthGeneralAndAdministrativeExpenses": 0,
    "growthSellingAndMarketingExpenses": 0,
    "growthOtherExpenses": 0,
    "growthOperatingExpenses": 0.2510575456659605,
    "growthCostAndExpenses": 0.2343682938731355,
    "growthInterestIncome": 0,
    "growthInterestExpense": 0,
    "growthDepreciationAndAmortization": -0.10263700041203132,
    "growthEBITDA": 0.4150725707824722,
    "growthOperatingIncome": 0.47952602917164566,
    "growthIncomeBeforeTax": 0.38766097129871224,
    "growthIncomeTaxExpense": 0.3878520763032849,
    "growthNetIncome": 0.387550334232594,
    "growthEPS": 0.36094674556213013,
    "growthEPSDiluted": 0.37423312883435605,
    "growthWeightedAverageShsOut": 0.01831608718098359,
    "growthWeightedAverageShsOutDil": 0.006918320577679768,
    "growthEBIT": 0.47952602917164566,
    "growthNonOperatingIncomeExcludingInterest": 0,
    "growthNetInterestIncome": -0.12102840462557539,
    "growthTotalOtherIncomeExpensesNet": -0.7090275509092889,
    "growthNetIncomeFromContinuingOperations": 0.387550334232594,
    "growthOtherAdjustmentsToNetIncome": 0,
    "growthNetIncomeDeductions": 0
  },
  {
    "symbol": "BKE",
    "date": "2008-01-31",
    "fiscalYear": "2007",
    "period": "FY",
    "reportedCurrency": "USD",
    "growthRevenue": 0.16943672015605368,
    "growthCostOfRevenue": 0.13195563266823646,
    "growthGrossProfit": 0.22778972958893273,
    "growthGrossProfitRatio": 0.04989838996321334,
    "growthResearchAndDevelopmentExpenses": 0,
    "growthGeneralAndAdministrativeExpenses": 0,
    "growthSellingAndMarketingExpenses": 0,
    "growthOtherExpenses": 0,
    "growthOperatingExpenses": 0.129531619028318,
    "growthCostAndExpenses": 0.1312661704943765,
    "growthInterestIncome": 0,
    "growthInterestExpense": 0,
    "growthDepreciationAndAmortization": 0.09928435546698071,
    "growthEBITDA": 0.21027154333801887,
    "growthOperatingIncome": 0.3873147644297086,
    "growthIncomeBeforeTax": 0.34930098917697294,
    "growthIncomeTaxExpense": 0.3475732359946794,
    "growthNetIncome": 0.3503032695689624,
    "growthEPS": 0.3100775193798449,
    "growthEPSDiluted": 0.314516129032258,
    "growthWeightedAverageShsOut": 0.0281474371409844,
    "growthWeightedAverageShsOutDil": 0.027900907187997218,
    "growthEBIT": 0.24501152714842198,
    "growthNonOperatingIncomeExcludingInterest": 1,
    "growthNetInterestIncome": 0.16920451562089786,
    "growthTotalOtherIncomeExpensesNet": 0.01671833480956599,
    "growthNetIncomeFromContinuingOperations": 0.3503032695689624,
    "growthOtherAdjustmentsToNetIncome": 0,
    "growthNetIncomeDeductions": 0
  },
  {
    "symbol": "BKE",
    "date": "2007-01-31",
    "fiscalYear": "2006",
    "period": "FY",
    "reportedCurrency": "USD",
    "growthRevenue": 0.05781868325946266,
    "growthCostOfRevenue": 0.0511198027766289,
    "growthGrossProfit": 0.06841958791576908,
    "growthGrossProfitRatio": 0.01002147612828439,
    "growthResearchAndDevelopmentExpenses": 0,
    "growthGeneralAndAdministrativeExpenses": -1,
    "growthSellingAndMarketingExpenses": -1,
    "growthOtherExpenses": 0,
    "growthOperatingExpenses": 0.08985184681776479,
    "growthCostAndExpenses": 0.06185334020749613,
    "growthInterestIncome": 0,
    "growthInterestExpense": 0,
    "growthDepreciationAndAmortization": 0.20776805251641137,
    "growthEBITDA": 0.07360730776149833,
    "growthOperatingIncome": 0.03536332905322188,
    "growthIncomeBeforeTax": 0.06802110497907696,
    "growthIncomeTaxExpense": 0.058548086053898295,
    "growthNetIncome": 0.07359457480830732,
    "growthEPS": 0.10256410256410266,
    "growthEPSDiluted": 0.09734513274336293,
    "growthWeightedAverageShsOut": -0.019739526138622437,
    "growthWeightedAverageShsOutDil": -0.021420875501712483,
    "growthEBIT": 0.06802110497907696,
    "growthNonOperatingIncomeExcludingInterest": -0.4750939082149273,
    "growthNetInterestIncome": 0.46810560801695894,
    "growthTotalOtherIncomeExpensesNet": 0.4750939082149273,
    "growthNetIncomeFromContinuingOperations": 0.07359457480830732,
    "growthOtherAdjustmentsToNetIncome": 0,
    "growthNetIncomeDeductions": 0
  },
  {
    "symbol": "BKE",
    "date": "2006-01-31",
    "fiscalYear": "2005",
    "period": "FY",
    "reportedCurrency": "USD",
    "growthRevenue": 0.06405103018025765,
    "growthCostOfRevenue": 0.02368664946425833,
    "growthGrossProfit": 0.13486451552529843,
    "growthGrossProfitRatio": 0.06655083568570642,
    "growthResearchAndDevelopmentExpenses": 0,
    "growthGeneralAndAdministrativeExpenses": 0,
    "growthSellingAndMarketingExpenses": 0,
    "growthOtherExpenses": 0,
    "growthOperatingExpenses": 0.09394370254723206,
    "growthCostAndExpenses": 0.042236207721467744,
    "growthInterestIncome": 0,
    "growthInterestExpense": 0,
    "growthDepreciationAndAmortization": -0.041778057346542954,
    "growthEBITDA": 0.21357445208553166,
    "growthOperatingIncome": 0.20434892381493405,
    "growthIncomeBeforeTax": 0.21525014003124907,
    "growthIncomeTaxExpense": 0.24076707431032382,
    "growthNetIncome": 0.2007217377223623,
    "growthEPS": 0.2999999999999999,
    "growthEPSDiluted": 0.3139534883720929,
    "growthWeightedAverageShsOut": -0.08257939735970124,
    "growthWeightedAverageShsOutDil": -0.08084842531843534,
    "growthEBIT": 0.3009688821561573,
    "growthNonOperatingIncomeExcludingInterest": 0,
    "growthNetInterestIncome": 0.3878042257288045,
    "growthTotalOtherIncomeExpensesNet": 0.3697986577181208,
    "growthNetIncomeFromContinuingOperations": 0.2007217377223623,
    "growthOtherAdjustmentsToNetIncome": 0,
    "growthNetIncomeDeductions": 0
  },
  {
    "symbol": "BKE",
    "date": "2005-01-31",
    "fiscalYear": "2004",
    "period": "FY",
    "reportedCurrency": "USD",
    "growthRevenue": 0.11380019866609906,
    "growthCostOfRevenue": 0.07165747889432335,
    "growthGrossProfit": 0.19633498695065038,
    "growthGrossProfitRatio": 0.07410196953726847,
    "growthResearchAndDevelopmentExpenses": 0,
    "growthGeneralAndAdministrativeExpenses": 0,
    "growthSellingAndMarketingExpenses": 0,
    "growthOtherExpenses": 0,
    "growthOperatingExpenses": 0.13613759462798136,
    "growthCostAndExpenses": 0.08795987336298162,
    "growthInterestIncome": 0,
    "growthInterestExpense": 0,
    "growthDepreciationAndAmortization": 0.30557076375581715,
    "growthEBITDA": 0.25504612293360124,
    "growthOperatingIncome": 0.314608140065552,
    "growthIncomeBeforeTax": 0.28260294173252165,
    "growthIncomeTaxExpense": 0.28534127108465196,
    "growthNetIncome": 0.2810490443028597,
    "growthEPS": 0.267605633802817,
    "growthEPSDiluted": 0.24637681159420297,
    "growthWeightedAverageShsOut": 0.020529148506537878,
    "growthWeightedAverageShsOutDil": 0.029906631289971168,
    "growthEBIT": 0.3174230297486643,
    "growthNonOperatingIncomeExcludingInterest": -1,
    "growthNetInterestIncome": 0,
    "growthTotalOtherIncomeExpensesNet": -0.046501706484641636,
    "growthNetIncomeFromContinuingOperations": 0.28355948810831677,
    "growthOtherAdjustmentsToNetIncome": 0,
    "growthNetIncomeDeductions": 0
  },
  {
    "symbol": "BKE",
    "date": "2004-01-31",
    "fiscalYear": "2003",
    "period": "FY",
    "reportedCurrency": "USD",
    "growthRevenue": 0.05425622101431207,
    "growthCostOfRevenue": 0.03846653285497509,
    "growthGrossProfit": 0.08661339496833349,
    "growthGrossProfitRatio": 0.030691945064146773,
    "growthResearchAndDevelopmentExpenses": 0,
    "growthGeneralAndAdministrativeExpenses": 0,
    "growthSellingAndMarketingExpenses": 0,
    "growthOtherExpenses": 0,
    "growthOperatingExpenses": 0.10474379760418975,
    "growthCostAndExpenses": 0.05446060135222622,
    "growthInterestIncome": 0,
    "growthInterestExpense": 0,
    "growthDepreciationAndAmortization": 0.17374889549361394,
    "growthEBITDA": 0.08038680393382232,
    "growthOperatingIncome": 0.052670655544394464,
    "growthIncomeBeforeTax": 0.047571892577041905,
    "growthIncomeTaxExpense": 0.03912524419361841,
    "growthNetIncome": 0.05242639720558882,
    "growthEPS": 0.0441176470588234,
    "growthEPSDiluted": 0.06153846153846142,
    "growthWeightedAverageShsOut": -0.005407953458362611,
    "growthWeightedAverageShsOutDil": -0.009228999126212879,
    "growthEBIT": 0.05003165178668879,
    "growthNonOperatingIncomeExcludingInterest": 7.0588235294117645,
    "growthNetInterestIncome": 0,
    "growthTotalOtherIncomeExpensesNet": -0.0021285653469561515,
    "growthNetIncomeFromContinuingOperations": 0.05000779423226812,
    "growthOtherAdjustmentsToNetIncome": 0,
    "growthNetIncomeDeductions": 0
  },
  {
    "symbol": "BKE",
    "date": "2003-01-31",
    "fiscalYear": "2002",
    "period": "FY",
    "reportedCurrency": "USD",
    "growthRevenue": 0.034625088355630766,
    "growthCostOfRevenue": 0.038082766854743974,
    "growthGrossProfit": 0.027610884970271813,
    "growthGrossProfitRatio": -0.006779464045831272,
    "growthResearchAndDevelopmentExpenses": 0,
    "growthGeneralAndAdministrativeExpenses": 0,
    "growthSellingAndMarketingExpenses": 0,
    "growthOtherExpenses": 0,
    "growthOperatingExpenses": 0.06203778259523072,
    "growthCostAndExpenses": 0.043764139025178485,
    "growthInterestIncome": 0,
    "growthInterestExpense": 0,
    "growthDepreciationAndAmortization": 0.026044671556910905,
    "growthEBITDA": 0.02365280045790475,
    "growthOperatingIncome": -0.031183887619531184,
    "growthIncomeBeforeTax": -0.03064045461526647,
    "growthIncomeTaxExpense": -0.04150629356080308,
    "growthNetIncome": -0.024283366806645973,
    "growthEPS": -0.042253521126760445,
    "growthEPSDiluted": -0.04411764705882357,
    "growthWeightedAverageShsOut": -0.018572140722108502,
    "growthWeightedAverageShsOutDil": 0.0136324873405411,
    "growthEBIT": -0.030824236269780824,
    "growthNonOperatingIncomeExcludingInterest": 0,
    "growthNetInterestIncome": 0,
    "growthTotalOtherIncomeExpensesNet": -0.025311203319502075,
    "growthNetIncomeFromContinuingOperations": -0.023948633680238574,
    "growthOtherAdjustmentsToNetIncome": 0,
    "growthNetIncomeDeductions": 0
  },
  {
    "symbol": "BKE",
    "date": "2002-01-31",
    "fiscalYear": "2001",
    "period": "FY",
    "reportedCurrency": "USD",
    "growthRevenue": -0.014263300165036224,
    "growthCostOfRevenue": 0.036713914953084445,
    "growthGrossProfit": -0.10367164576286617,
    "growthGrossProfitRatio": -0.09070205608366567,
    "growthResearchAndDevelopmentExpenses": 0,
    "growthGeneralAndAdministrativeExpenses": 0,
    "growthSellingAndMarketingExpenses": 0,
    "growthOtherExpenses": -1,
    "growthOperatingExpenses": 0.0090625,
    "growthCostAndExpenses": 0.030019670146769557,
    "growthInterestIncome": 0,
    "growthInterestExpense": 0,
    "growthDepreciationAndAmortization": 0.022415100699418555,
    "growthEBITDA": -0.20442247937426336,
    "growthOperatingIncome": -0.07500831686268371,
    "growthIncomeBeforeTax": -0.05227343025054129,
    "growthIncomeTaxExpense": -0.04651854790716128,
    "growthNetIncome": -0.048223129724563385,
    "growthEPS": -0.05333333333333338,
    "growthEPSDiluted": -0.055555555555555455,
    "growthWeightedAverageShsOut": 0.04665016212843799,
    "growthWeightedAverageShsOutDil": 0.04665016212843799,
    "growthEBIT": -0.24728888322690573,
    "growthNonOperatingIncomeExcludingInterest": 1,
    "growthNetInterestIncome": 0,
    "growthTotalOtherIncomeExpensesNet": 0.24870466321243523,
    "growthNetIncomeFromContinuingOperations": -0.05560824208983533,
    "growthOtherAdjustmentsToNetIncome": 0,
    "growthNetIncomeDeductions": 0
  },
  {
    "symbol": "BKE",
    "date": "2001-01-31",
    "fiscalYear": "2000",
    "period": "FY",
    "reportedCurrency": "USD",
    "growthRevenue": 0.047189808428710664,
    "growthCostOfRevenue": 0.07199876727632272,
    "growthGrossProfit": 0.006342628808220047,
    "growthGrossProfitRatio": -0.03900647183811334,
    "growthResearchAndDevelopmentExpenses": 0,
    "growthGeneralAndAdministrativeExpenses": 0,
    "growthSellingAndMarketingExpenses": 0,
    "growthOtherExpenses": 0.18284789644012944,
    "growthOperatingExpenses": -0.05732634183703529,
    "growthCostAndExpenses": 0.0375391687127544,
    "growthInterestIncome": 0,
    "growthInterestExpense": 0,
    "growthDepreciationAndAmortization": 0.2001415857605178,
    "growthEBITDA": 0.11572026300059773,
    "growthOperatingIncome": -0.10399424884275495,
    "growthIncomeBeforeTax": -0.07622361167137287,
    "growthIncomeTaxExpense": -0.08801447308909996,
    "growthNetIncome": -0.07647247632803723,
    "growthEPS": -0.025974025974025997,
    "growthEPSDiluted": -0.013698630136986314,
    "growthWeightedAverageShsOut": -0.008031377747148282,
    "growthWeightedAverageShsOutDil": -0.008031377747148282,
    "growthEBIT": 0.10108360218824519,
    "growthNonOperatingIncomeExcludingInterest": 0,
    "growthNetInterestIncome": 0,
    "growthTotalOtherIncomeExpensesNet": 0.5665584415584416,
    "growthNetIncomeFromContinuingOperations": -0.06925052158562028,
    "growthOtherAdjustmentsToNetIncome": 0,
    "growthNetIncomeDeductions": 0
  },
  {
    "symbol": "BKE",
    "date": "2000-01-31",
    "fiscalYear": "1999",
    "period": "FY",
    "reportedCurrency": "USD",
    "growthRevenue": 0.11135247114530926,
    "growthCostOfRevenue": 0.11517422434367541,
    "growthGrossProfit": 0.10511682242990654,
    "growthGrossProfitRatio": -0.005610865026707876,
    "growthResearchAndDevelopmentExpenses": 0,
    "growthGeneralAndAdministrativeExpenses": 0,
    "growthSellingAndMarketingExpenses": 0,
    "growthOtherExpenses": 0.37333333333333335,
    "growthOperatingExpenses": 0.1078981723237598,
    "growthCostAndExpenses": 0.11322614470464873,
    "growthInterestIncome": 0,
    "growthInterestExpense": 0,
    "growthDepreciationAndAmortization": 0.37333333333333335,
    "growthEBITDA": 0.1342372881355932,
    "growthOperatingIncome": 0.10100386100386101,
    "growthIncomeBeforeTax": 0.09974121996303142,
    "growthIncomeTaxExpense": 0.1,
    "growthNetIncome": 0.09958823529411764,
    "growthEPS": 0.11594202898550736,
    "growthEPSDiluted": 0.12307692307692301,
    "growthWeightedAverageShsOut": -0.05513817044043976,
    "growthWeightedAverageShsOutDil": -0.10390506986302685,
    "growthEBIT": 0.10100386100386101,
    "growthNonOperatingIncomeExcludingInterest": 0,
    "growthNetInterestIncome": 0,
    "growthTotalOtherIncomeExpensesNet": 0.07130434782608695,
    "growthNetIncomeFromContinuingOperations": 0.09958823529411764,
    "growthOtherAdjustmentsToNetIncome": 0,
    "growthNetIncomeDeductions": 0
  },
  {
    "symbol": "BKE",
    "date": "1999-01-31",
    "fiscalYear": "1998",
    "period": "FY",
    "reportedCurrency": "USD",
    "growthRevenue": 0.2612915266890631,
    "growthCostOfRevenue": 0.23891188645771733,
    "growthGrossProfit": 0.29959514170040485,
    "growthGrossProfitRatio": 0.030368566174541024,
    "growthResearchAndDevelopmentExpenses": 0,
    "growthGeneralAndAdministrativeExpenses": 0,
    "growthSellingAndMarketingExpenses": 0,
    "growthOtherExpenses": 0.3584905660377358,
    "growthOperatingExpenses": 0.21394611727416799,
    "growthCostAndExpenses": 0.23212747631352282,
    "growthInterestIncome": 0,
    "growthInterestExpense": 0,
    "growthDepreciationAndAmortization": 0.3584905660377358,
    "growthEBITDA": 0.43902439024390244,
    "growthOperatingIncome": 0.45098039215686275,
    "growthIncomeBeforeTax": 0.446524064171123,
    "growthIncomeTaxExpense": 0.425531914893617,
    "growthNetIncome": 0.4592274678111588,
    "growthEPS": 0.40816326530612235,
    "growthEPSDiluted": 0.38297872340425543,
    "growthWeightedAverageShsOut": 0.034545895976068865,
    "growthWeightedAverageShsOutDil": 0.04126354827980156,
    "growthEBIT": 0.45098039215686275,
    "growthNonOperatingIncomeExcludingInterest": 0,
    "growthNetInterestIncome": 0,
    "growthTotalOtherIncomeExpensesNet": 0.35294117647058826,
    "growthNetIncomeFromContinuingOperations": 0.4592274678111588,
    "growthOtherAdjustmentsToNetIncome": 0,
    "growthNetIncomeDeductions": 0
  },
  {
    "symbol": "BKE",
    "date": "1998-01-31",
    "fiscalYear": "1997",
    "period": "FY",
    "reportedCurrency": "USD",
    "growthRevenue": 0.29796511627906974,
    "growthCostOfRevenue": 0.25166543301258326,
    "growthGrossProfit": 0.3856942496493689,
    "growthGrossProfitRatio": 0.0675897466366878,
    "growthResearchAndDevelopmentExpenses": 0,
    "growthGeneralAndAdministrativeExpenses": 0,
    "growthSellingAndMarketingExpenses": 0,
    "growthOtherExpenses": 0,
    "growthOperatingExpenses": 0.2421259842519685,
    "growthCostAndExpenses": 0.2490586336740183,
    "growthInterestIncome": 0,
    "growthInterestExpense": 0,
    "growthDepreciationAndAmortization": 0,
    "growthEBITDA": 0.5891472868217055,
    "growthOperatingIncome": 0.7414634146341463,
    "growthIncomeBeforeTax": 0.7314814814814815,
    "growthIncomeTaxExpense": 0.7625,
    "growthNetIncome": 0.7132352941176471,
    "growthEPS": 0.6896551724137931,
    "growthEPSDiluted": 0.6785714285714283,
    "growthWeightedAverageShsOut": 0.013379458074899101,
    "growthWeightedAverageShsOutDil": 0.0289691017269246,
    "growthEBIT": 0.7414634146341463,
    "growthNonOperatingIncomeExcludingInterest": 0,
    "growthNetInterestIncome": 0,
    "growthTotalOtherIncomeExpensesNet": 0.5454545454545454,
    "growthNetIncomeFromContinuingOperations": 0.7132352941176471,
    "growthOtherAdjustmentsToNetIncome": 0,
    "growthNetIncomeDeductions": 0
  },
  {
    "symbol": "BKE",
    "date": "1997-01-31",
    "fiscalYear": "1996",
    "period": "FY",
    "reportedCurrency": "USD",
    "growthRevenue": 0.1979106210098665,
    "growthCostOfRevenue": 0.1966341895482728,
    "growthGrossProfit": 0.20033670033670034,
    "growthGrossProfitRatio": 0.0020252588702060555,
    "growthResearchAndDevelopmentExpenses": 0,
    "growthGeneralAndAdministrativeExpenses": 0,
    "growthSellingAndMarketingExpenses": 0,
    "growthOtherExpenses": -0.018518518518518517,
    "growthOperatingExpenses": 0.13646532438478748,
    "growthCostAndExpenses": 0.17956852791878172,
    "growthInterestIncome": 0,
    "growthInterestExpense": 0,
    "growthDepreciationAndAmortization": -0.018518518518518517,
    "growthEBITDA": 0.2835820895522388,
    "growthOperatingIncome": 0.3945578231292517,
    "growthIncomeBeforeTax": 0.3584905660377358,
    "growthIncomeTaxExpense": 0.3114754098360656,
    "growthNetIncome": 0.3877551020408163,
    "growthEPS": 0.38095238095238093,
    "growthEPSDiluted": 0.33333333333333354,
    "growthWeightedAverageShsOut": 0.024291083546230656,
    "growthWeightedAverageShsOutDil": 0.03479222906488194,
    "growthEBIT": 0.3945578231292517,
    "growthNonOperatingIncomeExcludingInterest": 0,
    "growthNetInterestIncome": 0,
    "growthTotalOtherIncomeExpensesNet": -0.08333333333333333,
    "growthNetIncomeFromContinuingOperations": 0.3877551020408163,
    "growthOtherAdjustmentsToNetIncome": 0,
    "growthNetIncomeDeductions": 0
  }
]