[
  {
    "symbol": "IRMD",
    "price": 86.44,
    "marketCap": 1104962520,
    "beta": 0.913,
    "lastDividend": 1.41,
    "range": "50.88-107.9",
    "change": -0.45,
    "changePercentage": -0.5179,
    "volume": 182195,
    "averageVolume": 91429,
    "companyName": "IRadimed Corporation",
    "currency": "USD",
    "cik": "0001325618",
    "isin": "US46266A1097",
    "cusip": "46266A109",
    "exchangeFullName": "NASDAQ Capital Market",
    "exchange": "NASDAQ",
    "industry": "Medical - Devices",
    "website": "https://www.iradimed.com",
    "description": "IRADIMED CORPORATION develops, manufactures, markets, and distributes magnetic resonance imaging (MRI) compatible medical devices, and related accessories and services in the United States and internationally. It offers MRidium MRI compatible intravenous (IV) infusion pump system with associated disposable IV tubing sets; and MRI compatible patient vital signs monitoring system. The company also provides non-magnetic IV poles, wireless remote displays/controls, side car pump modules, dose error reduction systems, and SpO2 monitoring with sensors and accessories. It serves hospitals, acute care facilities, and outpatient imaging centers. The company sells its products through direct field sales representatives, regional sales directors, clinical support representatives, and independent distributors. IRADIMED CORPORATION was incorporated in 1992 and is headquartered in Winter Springs, Florida.",
    "ceo": "Roger E. Susi",
    "sector": "Healthcare",
    "country": "US",
    "fullTimeEmployees": "160",
    "phone": "407 677 8022",
    "address": "1025 Willa Springs Drive",
    "city": "Winter Springs",
    "state": "FL",
    "zip": "32708",
    "image": "https://images.financialmodelingprep.com/symbol/IRMD.png",
    "ipoDate": "2014-07-16",
    "defaultImage": false,
    "isEtf": false,
    "isActivelyTrading": true,
    "isAdr": false,
    "isFund": false
  }
]