[
  {
    "symbol": "AVGO",
    "fiscalYear": 2025,
    "period": "FY",
    "reportedCurrency": null,
    "date": "2025-11-02",
    "data": {
      "Americas": 18939000000,
      "Asia Pacific": 35896000000,
      "EMEA": 9052000000
    }
  },
  {
    "symbol": "AVGO",
    "fiscalYear": 2024,
    "period": "FY",
    "reportedCurrency": "USD",
    "date": "2024-11-03",
    "data": {
      "Americas": 14970000000,
      "Asia Pacific": 28422000000,
      "EMEA": 8182000000
    }
  },
  {
    "symbol": "AVGO",
    "fiscalYear": 2023,
    "period": "FY",
    "reportedCurrency": "USD",
    "date": "2023-10-29",
    "data": {
      "Americas": 8279000000,
      "Asia Pacific": 23920000000,
      "EMEA": 3620000000
    }
  },
  {
    "symbol": "AVGO",
    "fiscalYear": 2022,
    "period": "FY",
    "reportedCurrency": "USD",
    "date": "2022-10-30",
    "data": {
      "Americas": 6944000000,
      "Asia Pacific": 22505000000,
      "EMEA": 3754000000
    }
  },
  {
    "symbol": "AVGO",
    "fiscalYear": 2021,
    "period": "FY",
    "reportedCurrency": "USD",
    "date": "2021-10-31",
    "data": {
      "Americas": 6099000000,
      "Asia Pacific": 17978000000,
      "EMEA": 3373000000
    }
  },
  {
    "symbol": "AVGO",
    "fiscalYear": 2020,
    "period": "FY",
    "reportedCurrency": "USD",
    "date": "2020-11-01",
    "data": {
      "Americas": 5834000000,
      "Asia Pacific": 15323000000,
      "EMEA": 2731000000
    }
  },
  {
    "symbol": "AVGO",
    "fiscalYear": 2019,
    "period": "FY",
    "reportedCurrency": "USD",
    "date": "2019-11-03",
    "data": {
      "Americas": 5149000000,
      "Asia Pacific": 15231000000,
      "EMEA": 2217000000
    }
  },
  {
    "symbol": "AVGO",
    "fiscalYear": 2018,
    "period": "FY",
    "reportedCurrency": "USD",
    "date": "2018-11-04",
    "data": {
      "Asia Pacific": 10305000000,
      "Americas": 2697000000
    }
  }
]